Workbook
Name UPDATE: 'Data Sheet'!$E$1

Sheet DCF
B1: HINDUSTAN UNILEVER
B7: DCF VALUATION
B10: Calculation for PV of FCFF | D10: ='[1]Intrinsic growth'!$I$2 -> 45717 | E10: =D10+365 -> 46082 | F10: =E10+365 -> 46447 | G10: =F10+366 -> 46813 | H10: =G10+365 -> 47178 | I10: =H10+365 -> 47543
B12: EBIT | D12: ='Intrinsic growth'!I40 -> 13488 | E12: =D12*(1+$C$22) -> 14150.261 | F12: =E12*(1+$C$22) -> 14845.039 | G12: =F12*(1+$C$22) -> 15573.93 | H12: =G12*(1+$C$22) -> 16338.61 | I12: =H12*(1+$C$22) -> 17140.836
B13: TAX | D13: 0.25 | E13: =D13 -> 0.25 | F13: =E13 -> 0.25 | G13: =F13 -> 0.25 | H13: =G13 -> 0.25 | I13: =H13 -> 0.25
B14: EBIT(1-T) | D14: =D12*(1-D13) -> 10116 | E14: =E12*(1-E13) -> 10612.696 | F14: =F12*(1-F13) -> 11133.779 | G14: =G12*(1-G13) -> 11680.448 | H14: =H12*(1-H13) -> 12253.957 | I14: =I12*(1-I13) -> 12855.627
B15: REINVESTMENT RATE | D15: ='Intrinsic growth'!I59 -> 0.110712 | E15: =($I$15-$D$15)/5+D15 -> 0.19687011 | F15: =($I$15-$D$15)/5+E15 -> 0.28302822 | G15: =($I$15-$D$15)/5+F15 -> 0.36918633 | H15: =($I$15-$D$15)/5+G15 -> 0.45534444 | I15: 0.54150255
B16: FCFF | D16: =D14*(1-D15) -> 8996.0375 | E16: =E14*(1-E15) -> 8523.3731 | F16: =F14*(1-F15) -> 7982.6054 | G16: =G14*(1-G15) -> 7368.186 | H16: =H14*(1-H15) -> 6674.1861 | I16: =I14*(1-I15) -> 5894.2721
B17: MID YEAR CONVENTION | E17: 0.5 | F17: =E17+1 -> 1.5 | G17: =F17+1 -> 2.5 | H17: =G17+1 -> 3.5 | I17: =H17+1 -> 4.5
B18: DISCOUNT RATE | E18: =1/((1+$C$24)^E17) -> 0.94240961 | F18: =1/((1+$C$24)^F17) -> 0.83698777 | G18: =1/((1+$C$24)^G17) -> 0.74335886 | H18: =1/((1+$C$24)^H17) -> 0.66020367 | I18: =1/((1+$C$24)^I17) -> 0.58635055
B20: PV OF FCFF | E20: =E16*E18 -> 8032.5087 | F20: =F16*F18 -> 6681.3431 | G20: =G16*G18 -> 5477.2063 | H20: =H16*H18 -> 4406.3221 | I20: =I16*I18 -> 3456.1097
B22: EXPECTED GROWTH | C22: 0.0491
B23: TERMINAL GROWTH | C23: 0.05
B24: WACC | C24: =WACC!I42 -> 0.12595385
B26: Calculation for Terminal Value
B28: FCFF(n+1) | C28: =I16*(1+C23) -> 6188.9857
B29: WACC | C29: =C24 -> 0.12595385
B30: TERMINAL GROWTH RATE | C30: =C23 -> 0.05
B31: TERMINAL VALUE | C31: =C28/(C29-C30) -> 81483.5
B33: Calculation for Equity Value Per Share
B35: PV OF FCFFs | C35: =SUM(E20:I20) -> 28053.49
B36: TERMINAL VALUE | C36: =C31 -> 81483.5
B37: PV OF TERMINAL VALUE | C37: =C36*I18 -> 47777.896
B38: ENTERPRISE VALUE | C38: =C37+C35 -> 75831.386
B40: ADD: CASH | C40: ='RAW FS'!N41 -> 7554
B41: LESS: DEBT | C41: =SUM('RAW FS'!N9:N10) -> 1
B43: EQUITY VALUE | C43: =C38+C40-C41 -> 83384.386
B44: NO. OF SHARES | C44: ='Data Sheet'!B6 -> 234.95913
B45: EQUITY VALUE PER SHARE | C45: =C43/C44 -> 354.8889
B47: SHARE PRICE | C47: 2166
B48: PREMIUM/DISCOUNT | C48: =C47/C45 -> 6.1033185

Sheet Relative Valuation
B1: HINDUSTAN UNILEVER
B5: Amount in Crores
B6: Comparable Company Valuation
D8: Market Share | J8: Financials | N8: Valuation
B9: Company | C9: Ticker | D9: Share Price | E9: Share Outstanding | F9: Equity Value | G9: Net Debt | H9: Enterprise Value | J9: Revenue | K9: EBITDA | L9: Net Income | N9: EV/REVENUE | O9: EV/EBITDA | P9: P/E
B10: Hind. Unilever | C10: HINDUNILVR | D10: ='Market Data'!D3 -> 2155.3 | E10: ='Market Data'!E3 -> 234.96 | F10: ='Market Data'!F3 -> 506409.29 | G10: ='Market Data'!I3 -> -5779 | H10: ='Market Data'!J3 -> 500630.29 | J10: ='Market Data'!K3 -> 63121 | K10: ='Market Data'!M3 -> 14568.327 | L10: ='Market Data'!N3 -> 14540 | N10: =$H10/J10 -> 7.9312794 | O10: =$H10/K10 -> 34.364296 | P10: =F10/L10 -> 34.828699
B11: ITC | C11: ITC | D11: ='Market Data'!D4 -> 304.25 | E11: ='Market Data'!E4 -> 1252.95 | F11: ='Market Data'!F4 -> 381210.04 | G11: ='Market Data'!I4 -> -3649.39 | H11: ='Market Data'!J4 -> 377560.65 | J11: ='Market Data'!K4 -> 75323.34 | K11: ='Market Data'!M4 -> 25399.03 | L11: ='Market Data'!N4 -> 35356.29 | N11: =$H11/J11 -> 5.0125319 | O11: =$H11/K11 -> 14.86516 | P11: =F11/L11 -> 10.781958
B12: Nestle India | C12: NESTLEIND | D12: ='Market Data'!D5 -> 1249.3 | E12: ='Market Data'!E5 -> 192.83 | F12: ='Market Data'!F5 -> 240902.52 | G12: ='Market Data'!I5 -> 381.2 | H12: ='Market Data'!J5 -> 241283.72 | J12: ='Market Data'!K5 -> 20201.56 | K12: ='Market Data'!M5 -> 4543.3308 | L12: ='Market Data'!N5 -> 3315.9 | N12: =$H12/J12 -> 11.943816 | O12: =$H12/K12 -> 53.107231 | P12: =F12/L12 -> 72.650719
B13: Varun Beverages | C13: VBL | D13: ='Market Data'!D6 -> 431.6 | E13: ='Market Data'!E6 -> 338.21 | F13: ='Market Data'!F6 -> 145971.44 | G13: ='Market Data'!I6 -> 509.69 | H13: ='Market Data'!J6 -> 146481.13 | J13: ='Market Data'!K6 -> 21685.37 | K13: ='Market Data'!M6 -> 5070.0395 | L13: ='Market Data'!N6 -> 3062.04 | N13: =$H13/J13 -> 6.7548364 | O13: =$H13/K13 -> 28.891516 | P13: =F13/L13 -> 47.671303
B14: Britannia Inds. | C14: BRITANNIA | D14: ='Market Data'!D7 -> 5557.5 | E14: ='Market Data'!E7 -> 24.09 | F14: ='Market Data'!F7 -> 133880.17 | G14: ='Market Data'!I7 -> 1883.82 | H14: ='Market Data'!J7 -> 135763.99 | J14: ='Market Data'!K7 -> 17942.67 | K14: ='Market Data'!M7 -> 3310.4226 | L14: ='Market Data'!N7 -> 2416.46 | N14: =$H14/J14 -> 7.5665436 | O14: =$H14/K14 -> 41.011076 | P14: =F14/L14 -> 55.403431
B15: Godrej Consumer | C15: GODREJCP | D15: ='Market Data'!D8 -> 1078.1 | E15: ='Market Data'!E8 -> 102.32 | F15: ='Market Data'!F8 -> 110311.19 | G15: ='Market Data'!I8 -> 3630.43 | H15: ='Market Data'!J8 -> 113941.62 | J15: ='Market Data'!K8 -> 14364.29 | K15: ='Market Data'!M8 -> 2901.5866 | L15: ='Market Data'!N8 -> 1821.6 | N15: =$H15/J15 -> 7.9322836 | O15: =$H15/K15 -> 39.268731 | P15: =F15/L15 -> 60.557308
B16: Tata Consumer | C16: TATACONSUM | D16: ='Market Data'!D9 -> 1093.7 | E16: ='Market Data'!E9 -> 98.96 | F16: ='Market Data'!F9 -> 108232.55 | G16: ='Market Data'!I9 -> -241.75 | H16: ='Market Data'!J9 -> 107990.8 | J16: ='Market Data'!K9 -> 17618.3 | K16: ='Market Data'!M9 -> 2371.4232 | L16: ='Market Data'!N9 -> 1471.5 | N16: =$H16/J16 -> 6.1294678 | O16: =$H16/K16 -> 45.538394 | P16: =F16/L16 -> 73.552533
B17: Marico | C17: MARICO | D17: ='Market Data'!D10 -> 763.25 | E17: ='Market Data'!E10 -> 129.81 | F17: ='Market Data'!F10 -> 99077.482 | G17: ='Market Data'!I10 -> -202 | H17: ='Market Data'!J10 -> 98875.482 | J17: ='Market Data'!K10 -> 10831 | K17: ='Market Data'!M10 -> 1885.6771 | L17: ='Market Data'!N10 -> 1750 | N17: =$H17/J17 -> 9.1289338 | O17: =$H17/K17 -> 52.435002 | P17: =F17/L17 -> 56.615704
B18: United Spirits | C18: UNITDSPR | D18: ='Market Data'!D11 -> 1268.2 | E18: ='Market Data'!E11 -> 72.74 | F18: ='Market Data'!F11 -> 92248.868 | G18: ='Market Data'!I11 -> -1618 | H18: ='Market Data'!J11 -> 90630.868 | J18: ='Market Data'!K11 -> 12069 | K18: ='Market Data'!M11 -> 2200.1787 | L18: ='Market Data'!N11 -> 1720 | N18: =$H18/J18 -> 7.5093933 | O18: =$H18/K18 -> 41.192503 | P18: =F18/L18 -> 53.633063
B19: Dabur India | C19: DABUR | D19: ='Market Data'!D12 -> 435.7 | E19: ='Market Data'!E12 -> 177.37 | F19: ='Market Data'!F12 -> 77280.109 | G19: ='Market Data'!I12 -> 723.42 | H19: ='Market Data'!J12 -> 78003.529 | J19: ='Market Data'!K12 -> 12563.09 | K19: ='Market Data'!M12 -> 2337.991 | L19: ='Market Data'!N12 -> 1819.42 | N19: =$H19/J19 -> 6.2089445 | O19: =$H19/K19 -> 33.363485 | P19: =F19/L19 -> 42.475134
B21: High | N21: =MAX(M10:N19) -> 11.943816 | O21: =MAX(N10:O19) -> 53.107231 | P21: =MAX(O10:P19) -> 73.552533
B22: 75th Percentile | N22: =QUARTILE(N10:N19,3) -> 7.9320326 | O22: =QUARTILE(O10:O19,3) -> 44.451921 | P22: =QUARTILE(P10:P19,3) -> 59.571907
B23: Average | N23: =AVERAGE(N10:N19) -> 7.6118031 | O23: =AVERAGE(O10:O19) -> 38.403739 | P23: =AVERAGE(P10:P19) -> 50.816985
B24: Median | N24: =MEDIAN(N10:N19) -> 7.5379685 | O24: =MEDIAN(O10:O19) -> 40.139904 | P24: =MEDIAN(P10:P19) -> 54.518247
B25: 25th Percentile | N25: =QUARTILE(N10:N19,1) -> 6.3454175 | O25: =QUARTILE(O10:O19,1) -> 33.613688 | P25: =QUARTILE(P10:P19,1) -> 43.774176
B26: Low | N26: =MIN(N10:N19) -> 5.0125319 | O26: =MIN(O10:O19) -> 14.86516 | P26: =MIN(P10:P19) -> 10.781958
B28: ='Data Sheet'!B1&" Comparable Valuation" -> HINDUSTAN UNILEVER LTD Comparable Valuation | N28: EV/REVENUE | O28: EV/EBITDA | P28: P/E
B30: Implied Enterprise Value | N30: =N$24*J10 -> 475804.11 | O30: =O$24*K10 -> 584771.23 | P30: =P$24*L10 -> 792695.31
B31: Net Debt | N31: =$G$10 -> -5779 | O31: =$G$10 -> -5779 | P31: =$G$10 -> -5779
B32: Implied Market Value | N32: =N30+N31 -> 470025.11 | O32: =O30+O31 -> 578992.23 | P32: =P30+P31 -> 786916.31
B33: Shares Outstanding | N33: =$E$10 -> 234.96 | O33: =$E$10 -> 234.96 | P33: =$E$10 -> 234.96
B35: Implied Market Value per Share | N35: =N32/N33 -> 2000.4473 | O35: =O32/O33 -> 2464.2162 | P35: =P32/P33 -> 3349.1501
B37: Source: Screener.in
N38: =IF(N35>$D$10,"Undervalued", "Overvalued") -> Overvalued | O38: =IF(O35>$D$10,"Undervalued", "Overvalued") -> Undervalued | P38: =IF(P35>$D$10,"Undervalued", "Overvalued") -> Undervalued

Sheet WACC
B1: HINDUSTAN UNILEVER
B5: Weighted Average Cost of Capital
B7: All figures are in INR unless stated otherwise
B9: Peer Comps
H10: Debt/ | I10: Debt/ | J10: Levered | K10: Unlevered
B11: Name of the Comp | D11: Country | E11: Total Debt | F11: Total Eq | G11: Tax Rate 1 | H11: Equity | I11: Capital | J11: Beta 2 | K11: Beta 3
B12: Hindustan Unilever | D12: India | E12: 1775 | F12: 504703.92 | G12: 0.25 | H12: =E12/F12 -> 0.0035169134 | I12: =E12/(E12+F12) -> 0.0035045881 | J12: ='Beta Calculation'!K17 -> 0.67290857 | K12: =J12/((1-G12)*H12+1) -> 0.67113831
B13: ITC | D13: India | E13: 362.97 | F13: 380707.86 | G13: 0.25 | H13: =E13/F13 -> 0.00095340821 | I13: =E13/(E13+F13) -> 0.00095250009 | J13: ='Peer Beta'!H113 -> 0.52972916 | K13: =J13/((1-G13)*H13+1) -> 0.52935064
B14: Hindustan Foods | D14: India | E14: 900.81 | F14: 6098.95 | G14: 0.25 | H14: =E14/F14 -> 0.14769919 | I14: =E14/(E14+F14) -> 0.12869156 | J14: ='Peer Beta'!L113 -> 1.0167885 | K14: =J14/((1-G14)*H14+1) -> 0.91538704
B15: Nestle India | D15: India | E15: 476.85 | F15: 240933.28 | G15: 0.25 | H15: =E15/F15 -> 0.0019791786 | I15: =E15/(E15+F15) -> 0.0019752692 | J15: ='Peer Beta'!P113 -> 0.81759042 | K15: =J15/((1-G15)*H15+1) -> 0.8163786
B16: Godrej Consumer | D16: India | E16: 4113.49 | F16: 109865.79 | G16: 0.25 | H16: =E16/F16 -> 0.037441045 | I16: =E16/(E16+F16) -> 0.036089805 | J16: ='Peer Beta'!T113 -> 0.89064309 | K16: =J16/((1-G16)*H16+1) -> 0.86631625
B17: Britannia Inds. | D17: India | E17: 2196.3 | F17: 133956.47 | G17: 0.25 | H17: =E17/F17 -> 0.016395625 | I17: =E17/(E17+F17) -> 0.016131144 | J17: ='Peer Beta'!X113 -> 0.54348 | K17: =J17/((1-G17)*H17+1) -> 0.53687816
G19: Average | H19: =IFERROR(AVERAGE(H12:H17),0) -> 0.034664227 | I19: =IFERROR(AVERAGE(I12:I17),0) -> 0.031224144 | J19: =IFERROR(AVERAGE(J12:J17),0) -> 0.74518995 | K19: =IFERROR(AVERAGE(K12:K17),0) -> 0.72257483
G20: Median | H20: =IFERROR(AVERAGE(H13:H18),0) -> 0.04089369 | I20: =IFERROR(AVERAGE(I13:I18),0) -> 0.036768055 | J20: =IFERROR(AVERAGE(J13:J18),0) -> 0.75964623 | K20: =IFERROR(AVERAGE(K13:K18),0) -> 0.73286214
B24: Cost of Debt | G24: Cost Of Equity
G25: Risk Free Rate | H25: 0.0691
B26: Pre Tax Cost Of Debt | D26: =Historicals!L25/Historicals!L55 -> 0.23968447 | G26: Levered Beta 4 | H26: =I36 -> 0.75533922
B27: Tax Rate | D27: 0.25 | G27: Equity Risk Premium | H27: =Rm!G15-WACC!H25 -> 0.07255
B28: Post Tax Cost Of Debt | D28: =D26*(1-D27) -> 0.17976335 | G28: Cost Of Equity | H28: =H25+H27*H26 -> 0.12389986
B31: Capital Structure | G31: Levered Beta
D33: Current | E33: Target | G33: Comps Median Unlevered Beta | I33: =K20 -> 0.73286214
B34: Total Debt | C34: =E12 -> 1775 | D34: =C34/C36 -> 0.0035045881 | E34: =I20 -> 0.036768055 | G34: Target Debt/ Equity | I34: =H20 -> 0.04089369
B35: Market Capitalization | C35: =F12 -> 504703.92 | D35: =C35/C36 -> 0.99649541 | E35: =1-E34 -> 0.96323195 | G35: Tax Rate | I35: =D27 -> 0.25
B36: Total Capitalization | C36: =SUM(C34:C35) -> 506478.92 | D36: =SUM(D34:D35) -> 1 | E36: =SUM(E34:E35) -> 1 | G36: Levered Beta | I36: =I33*(1+(1-I35)*I34) -> 0.75533922
B38: Debt/Equity | C38: =C34/C35 -> 0.0035169134 | G38: Weighted Average Cost of Capital
G40: Weighted Cost of Debt | I40: =D28*E34 -> 0.0066095487
B41: 1. Tax Rate considered as Marginal Tax Rate for the country | G41: Weighted Cost of Equity | I41: =H28*E35 -> 0.1193443
B42: 2. Levered Beta is based on 5 year monthly data | G42: WACC | I42: =I40+I41 -> 0.12595385
B43: 3. Unlevered Beta = Levered Beta/(1+(1-Tax Rate) x Debt/Equity)
B44: 4. Levered Beta = Unlevered Beta*(1+(1-Tax Rate) x Debt/Equity)

Sheet Forecasting
B1: HINDUSTAN UNILEVER
B5: FORECASTING BASED ON SALES AND EBITDA GROWTH
B8: ='Data Sheet'!$B$1&" - "&'Data Sheet'!A17 -> HINDUSTAN UNILEVER LTD - Sales | G8: ='Data Sheet'!$B$1&" - "&Historicals!B22 -> HINDUSTAN UNILEVER LTD - EBITDA | L8: ='Data Sheet'!$B$1&" - "&Historicals!B42 -> HINDUSTAN UNILEVER LTD - EPS
B9: Year Weight | C9: Year | D9: Sales | E9: Sales Growth | G9: Year Weight | H9: Year | I9: EBITDA | J9: EBITDA Growth | L9: Year Weight | M9: Year | N9: EPS | O9: EPS Growth
B10: 1 | C10: ='Data Sheet'!$B$16 -> 42460 | D10: {=TRANSPOSE('Data Sheet'!B17:K17)} -> 32186 | G10: 1 | H10: ='Data Sheet'!$B$16 -> 42460 | I10: {=TRANSPOSE(Historicals!C22:L22)} -> 5910 | L10: 1 | M10: ='Data Sheet'!$B$16 -> 42460 | N10: {=TRANSPOSE(Historicals!C42:L42)} -> 16.937012
B11: =B10+1 -> 2 | C11: =C10+365 -> 42825 | D11: 33162 | E11: =D11/D10-1 -> 0.030323743 | G11: =G10+1 -> 2 | H11: =H10+365 -> 42825 | I11: 6328 | J11: =I11/I10-1 -> 0.07072758 | L11: =L10+1 -> 2 | M11: =M10+365 -> 42825 | N11: 17.945756 | O11: =N11/N10-1 -> 0.059558573
B12: =B11+1 -> 3 | C12: =C11+365 -> 43190 | D12: 35545 | E12: =D12/D11-1 -> 0.071859357 | G12: =G11+1 -> 3 | H12: =H11+365 -> 43190 | I12: 7499 | J12: =I12/I11-1 -> 0.18505057 | L12: =L11+1 -> 3 | M12: =M11+365 -> 43190 | N12: 22.517903 | O12: =N12/N11-1 -> 0.25477591
B13: =B12+1 -> 4 | C13: =C12+365 -> 43555 | D13: 39310 | E13: =D13/D12-1 -> 0.10592207 | G13: =G12+1 -> 4 | H13: =H12+365 -> 43555 | I13: 8880 | J13: =I13/I12-1 -> 0.18415789 | L13: =L12+1 -> 4 | M13: =M12+365 -> 43555 | N13: 26.507137 | O13: =N13/N12-1 -> 0.17715836
B14: =B13+1 -> 5 | C14: =C13+365 -> 43920 | D14: 39783 | E14: =D14/D13-1 -> 0.012032562 | G14: =G13+1 -> 5 | H14: =H13+365 -> 43920 | I14: 9861 | J14: =I14/I13-1 -> 0.11047297 | L14: =L13+1 -> 5 | M14: =M13+365 -> 43920 | N14: 29.249815 | O14: =N14/N13-1 -> 0.10346941
B15: =B14+1 -> 6 | C15: =C14+365 -> 44285 | D15: 47028 | E15: =D15/D14-1 -> 0.18211296 | G15: =G14+1 -> 6 | H15: =H14+365 -> 44285 | I15: 11626 | J15: =I15/I14-1 -> 0.17898793 | L15: =L14+1 -> 6 | M15: =M14+365 -> 44285 | N15: 33.320565 | O15: =N15/N14-1 -> 0.13917182
B16: =B15+1 -> 7 | C16: =C15+365 -> 44650 | D16: 52446 | E16: =D16/D15-1 -> 0.11520796 | G16: =G15+1 -> 7 | H16: =H15+365 -> 44650 | I16: 12857 | J16: =I16/I15-1 -> 0.10588336 | L16: =L15+1 -> 7 | M16: =M15+365 -> 44650 | N16: 36.912666 | O16: =N16/N15-1 -> 0.10780432
B17: =B16+1 -> 8 | C17: =C16+365 -> 45015 | D17: 60580 | E17: =D17/D16-1 -> 0.15509286 | G17: =G16+1 -> 8 | H17: =H16+365 -> 45015 | I17: 14147 | J17: =I17/I16-1 -> 0.10033445 | L17: =L16+1 -> 8 | M17: =M16+365 -> 45015 | N17: 41.262343 | O17: =N17/N16-1 -> 0.11783697
B18: =B17+1 -> 9 | C18: =C17+365 -> 45380 | D18: 61896 | E18: =D18/D17-1 -> 0.021723341 | G18: =G17+1 -> 9 | H18: =H17+365 -> 45380 | I18: 14659 | J18: =I18/I17-1 -> 0.036191419 | L18: =L17+1 -> 9 | M18: =M17+365 -> 45380 | N18: 40.283453 | O18: =N18/N17-1 -> -0.023723569
B19: =B18+1 -> 10 | C19: =C18+365 -> 45745 | D19: 63121 | E19: =D19/D18-1 -> 0.019791263 | G19: =G18+1 -> 10 | H19: =H18+365 -> 45745 | I19: 14843 | J19: =I19/I18-1 -> 0.012552016 | L19: =L18+1 -> 10 | M19: =M18+365 -> 45745 | N19: 39.789751 | O19: =N19/N18-1 -> -0.012255679
B20: =B19+1 -> 11 | C20: =C19+365 -> 46110 | D20: =FORECAST(B20,_xlfn.ANCHORARRAY($D$10),$B$10:$B$19) -> 68218.4 | E20: =D20/D19-1 -> 0.080756008 | G20: =G19+1 -> 11 | H20: =H19+365 -> 46110 | I20: =FORECAST(G20,_xlfn.ANCHORARRAY($I$10),$G$10:$G$19) -> 16849.333 | J20: =I20/I19-1 -> 0.13517034 | L20: =L19+1 -> 11 | M20: =M19+365 -> 46110 | N20: =FORECAST(L20,$N$10:$N$19,$L$10:$L$19) -> 46.840909 | O20: =N20/N19-1 -> 0.17721039
B21: =B20+1 -> 12 | C21: =C20+365 -> 46475 | D21: =FORECAST(B21,_xlfn.ANCHORARRAY($D$10),$B$10:$B$19) -> 72166.164 | E21: =D21/D20-1 -> 0.057869484 | G21: =G20+1 -> 12 | H21: =H20+365 -> 46475 | I21: =FORECAST(G21,_xlfn.ANCHORARRAY($I$10),$G$10:$G$19) -> 17974.485 | J21: =I21/I20-1 -> 0.066777213 | L21: =L20+1 -> 12 | M21: =M20+365 -> 46475 | N21: =FORECAST(L21,$N$10:$N$19,$L$10:$L$19) -> 49.816958 | O21: =N21/N20-1 -> 0.063535251
B22: =B21+1 -> 13 | C22: =C21+365 -> 46840 | D22: =FORECAST(B22,_xlfn.ANCHORARRAY($D$10),$B$10:$B$19) -> 76113.927 | E22: =D22/D21-1 -> 0.054703804 | G22: =G21+1 -> 13 | H22: =H21+365 -> 46840 | I22: =FORECAST(G22,_xlfn.ANCHORARRAY($I$10),$G$10:$G$19) -> 19099.636 | J22: =I22/I21-1 -> 0.062597149 | L22: =L21+1 -> 13 | M22: =M21+365 -> 46840 | N22: =FORECAST(L22,$N$10:$N$19,$L$10:$L$19) -> 52.793007 | O22: =N22/N21-1 -> 0.059739675
B23: =B22+1 -> 14 | C23: =C22+365 -> 47205 | D23: =FORECAST(B23,_xlfn.ANCHORARRAY($D$10),$B$10:$B$19) -> 80061.691 | E23: =D23/D22-1 -> 0.051866508 | G23: =G22+1 -> 14 | H23: =H22+365 -> 47205 | I23: =FORECAST(G23,_xlfn.ANCHORARRAY($I$10),$G$10:$G$19) -> 20224.788 | J23: =I23/I22-1 -> 0.058909578 | L23: =L22+1 -> 14 | M23: =M22+365 -> 47205 | N23: =FORECAST(L23,$N$10:$N$19,$L$10:$L$19) -> 55.769056 | O23: =N23/N22-1 -> 0.056372029
B24: =B23+1 -> 15 | C24: =C23+365 -> 47570 | D24: =FORECAST(B24,_xlfn.ANCHORARRAY($D$10),$B$10:$B$19) -> 84009.455 | E24: =D24/D23-1 -> 0.049309021 | G24: =G23+1 -> 15 | H24: =H23+365 -> 47570 | I24: =FORECAST(G24,_xlfn.ANCHORARRAY($I$10),$G$10:$G$19) -> 21349.939 | J24: =I24/I23-1 -> 0.055632302 | L24: =L23+1 -> 15 | M24: =M23+365 -> 47570 | N24: =FORECAST(L24,$N$10:$N$19,$L$10:$L$19) -> 58.745105 | O24: =N24/N23-1 -> 0.053363803

Sheet Intrinsic growth
B1: HINDUSTAN UNILEVER
B5: Calculation of ROIC | E5: ='RAW FS'!J$4 -> 44256 | F5: ='RAW FS'!K$4 -> 44621 | G5: ='RAW FS'!L$4 -> 44986 | H5: ='RAW FS'!M$4 -> 45352 | I5: ='RAW FS'!N$4 -> 45717
B7: Current Assets
B8: ='RAW FS'!B39 -> Inventories | E8: ='RAW FS'!J39 -> 3579 | F8: ='RAW FS'!K39 -> 4096 | G8: ='RAW FS'!L39 -> 4251 | H8: ='RAW FS'!M39 -> 4022 | I8: ='RAW FS'!N39 -> 4415
B9: ='RAW FS'!B40 -> Trade receivables + | E9: ='RAW FS'!J40 -> 1758 | F9: ='RAW FS'!K40 -> 2236 | G9: ='RAW FS'!L40 -> 3079 | H9: ='RAW FS'!M40 -> 2997 | I9: ='RAW FS'!N40 -> 3819
B10: ='RAW FS'!B41 -> Cash Equivalents | E10: ='RAW FS'!J41 -> 4471 | F10: ='RAW FS'!K41 -> 3846 | G10: ='RAW FS'!L41 -> 4678 | H10: ='RAW FS'!M41 -> 7559 | I10: ='RAW FS'!N41 -> 7554
B11: ='RAW FS'!B42 -> Loans n Advances | E11: ='RAW FS'!J42 -> 78 | F11: ='RAW FS'!K42 -> 170 | G11: ='RAW FS'!L42 -> 188 | H11: ='RAW FS'!M42 -> 172 | I11: ='RAW FS'!N42 -> 242
B12: ='RAW FS'!B43 -> Other asset items | E12: ='RAW FS'!J43 -> 3957 | F12: ='RAW FS'!K43 -> 3851 | G12: ='RAW FS'!L43 -> 4189 | H12: ='RAW FS'!M43 -> 4345 | I12: ='RAW FS'!N43 -> 4679
B13: Total Current Assets | E13: =SUM(E8:E12) -> 13843 | F13: =SUM(F8:F12) -> 14199 | G13: =SUM(G8:G12) -> 16385 | H13: =SUM(H8:H12) -> 19095 | I13: =SUM(I8:I12) -> 20709
B15: Current Liabilities
B16: ='RAW FS'!B16 -> Trade Payables | E16: ='RAW FS'!J16 -> 8802 | F16: ='RAW FS'!K16 -> 9068 | G16: ='RAW FS'!L16 -> 9574 | H16: ='RAW FS'!M16 -> 10486 | I16: ='RAW FS'!N16 -> 11315
B17: ='RAW FS'!B17 -> Advance from Customers | E17: ='RAW FS'!J17 -> 96 | F17: ='RAW FS'!K17 -> 119 | G17: ='RAW FS'!L17 -> 98 | H17: ='RAW FS'!M17 -> 91 | I17: ='RAW FS'!N17 -> 105
B18: ='RAW FS'!B18 -> Other liability items | E18: ='RAW FS'!J18 -> 12148 | F18: ='RAW FS'!K18 -> 11189 | G18: ='RAW FS'!L18 -> 11664 | H18: ='RAW FS'!M18 -> 15005 | I18: ='RAW FS'!N18 -> 17186
B19: Total Liabilities | E19: =SUM(E16:E18) -> 21046 | F19: =SUM(F16:F18) -> 20376 | G19: =SUM(G16:G18) -> 21336 | H19: =SUM(H16:H18) -> 25582 | I19: =SUM(I16:I18) -> 28606
A21: # | B21: Net Working Capital | E21: =E13-E19 -> -7203 | F21: =F13-F19 -> -6177 | G21: =G13-G19 -> -4951 | H21: =H13-H19 -> -6487 | I21: =I13-I19 -> -7897
B24: Non Current Assets
B25: ='RAW FS'!B22 -> Land | E25: ='RAW FS'!J22 -> 477 | F25: ='RAW FS'!K22 -> 477 | G25: ='RAW FS'!L22 -> 609 | H25: ='RAW FS'!M22 -> 633 | I25: ='RAW FS'!N22 -> 628
B26: ='RAW FS'!B23 -> Building | E26: ='RAW FS'!J23 -> 2602 | F26: ='RAW FS'!K23 -> 2788 | G26: ='RAW FS'!L23 -> 3101 | H26: ='RAW FS'!M23 -> 3590 | I26: ='RAW FS'!N23 -> 3833
B27: ='RAW FS'!B24 -> Plant Machinery | E27: ='RAW FS'!J24 -> 6097 | F27: ='RAW FS'!K24 -> 6566 | G27: ='RAW FS'!L24 -> 7612 | H27: ='RAW FS'!M24 -> 8946 | I27: ='RAW FS'!N24 -> 9900
B28: ='RAW FS'!B25 -> Equipments | E28: ='RAW FS'!J25 -> 175 | F28: ='RAW FS'!K25 -> 181 | G28: ='RAW FS'!L25 -> 185 | H28: ='RAW FS'!M25 -> 206 | I28: ='RAW FS'!N25 -> 245
B29: ='RAW FS'!B26 -> Furniture n fittings | E29: ='RAW FS'!J26 -> 156 | F29: ='RAW FS'!K26 -> 152 | G29: ='RAW FS'!L26 -> 161 | H29: ='RAW FS'!M26 -> 165 | I29: ='RAW FS'!N26 -> 174
B30: ='RAW FS'!B27 -> Railway sidings | E30: ='RAW FS'!J27 -> 0 | F30: ='RAW FS'!K27 -> 0 | G30: ='RAW FS'!L27 -> 0 | H30: ='RAW FS'!M27 -> 0 | I30: ='RAW FS'!N27 -> 0
B31: ='RAW FS'!B28 -> Vehicles | E31: ='RAW FS'!J28 -> 0 | F31: ='RAW FS'!K28 -> 0 | G31: ='RAW FS'!L28 -> 33 | H31: ='RAW FS'!M28 -> 39 | I31: ='RAW FS'!N28 -> 102
B32: ='RAW FS'!B29 -> Intangible Assets | E32: ='RAW FS'!J29 -> 45262 | F32: ='RAW FS'!K29 -> 45262 | G32: ='RAW FS'!L29 -> 45692 | H32: ='RAW FS'!M29 -> 45692 | I32: ='RAW FS'!N29 -> 45692
B33: ='RAW FS'!B30 -> Other fixed assets | E33: ='RAW FS'!J30 -> 155 | F33: ='RAW FS'!K30 -> 152 | G33: ='RAW FS'!L30 -> 171 | H33: ='RAW FS'!M30 -> 180 | I33: ='RAW FS'!N30 -> 190
B35: ='RAW FS'!B31 -> Gross Block | E35: =SUM(E25:E33) -> 54924 | F35: =SUM(F25:F33) -> 55578 | G35: =SUM(G25:G33) -> 57564 | H35: =SUM(H25:H33) -> 59451 | I35: =SUM(I25:I33) -> 60764
B36: ='RAW FS'!B32 -> Accumulated Depreciation | E36: ='RAW FS'!J32 -> 3481 | F36: ='RAW FS'!K32 -> 4105 | G36: ='RAW FS'!L32 -> 4886 | H36: ='RAW FS'!M32 -> 5707 | I36: ='RAW FS'!N32 -> 6429
B37: ='RAW FS'!B33 -> Net Block | E37: =SUM(E35:E36) -> 58405 | F37: =SUM(F35:F36) -> 59683 | G37: =SUM(G35:G36) -> 62450 | H37: =SUM(H35:H36) -> 65158 | I37: =SUM(I35:I36) -> 67193
A39: # | B39: Invested Capital | E39: =E37+E21 -> 51202 | F39: =F37+F21 -> 53506 | G39: =G37+G21 -> 57499 | H39: =H37+H21 -> 58671 | I39: =I37+I21 -> 59296
B40: EBIT | E40: =Historicals!H22-Historicals!H28 -> 10552 | F40: =Historicals!I22-Historicals!I28 -> 11766 | G40: =Historicals!J22-Historicals!J28 -> 13010 | H40: =Historicals!K22-Historicals!K28 -> 13443 | I40: =Historicals!L22-Historicals!L28 -> 13488
A42: # | B42: ROIC | E42: =E40/E39 -> 0.2060857 | F42: =F40/F39 -> 0.21990057 | G42: =G40/G39 -> 0.2262648 | H42: =H40/H39 -> 0.22912512 | I42: =I40/I39 -> 0.22746897
B45: Calculation of Reinvestment Rate | E45: ='RAW FS'!J$4 -> 44256 | F45: ='RAW FS'!K$4 -> 44621 | G45: ='RAW FS'!L$4 -> 44986 | H45: ='RAW FS'!M$4 -> 45352 | I45: ='RAW FS'!N$4 -> 45717
B47: Net CAPEX | E47: =-1*SUM('Cash Flow Data'!J16:J17) -> 4066 | F47: =-1*SUM('Cash Flow Data'!K16:K17) -> 1053 | G47: =-1*SUM('Cash Flow Data'!L16:L17) -> 1011 | H47: =-1*SUM('Cash Flow Data'!M16:M17) -> 1457 | I47: =-1*SUM('Cash Flow Data'!N16:N17) -> 1262
B48: Change in Working Cap | F48: =F21-E21 -> 1026 | G48: =G21-F21 -> 1226 | H48: =H21-G21 -> -1536 | I48: =I21-H21 -> -1410
B50: EBIT | E50: =E40 -> 10552 | F50: =F40 -> 11766 | G50: =G40 -> 13010 | H50: =H40 -> 13443 | I50: =I40 -> 13488
B51: Tax | E51: 0.25 | F51: 0.25 | G51: 0.25 | H51: 0.25 | I51: 0.25
B52: EBIT(1-t) | E52: =E50*(1-E51) -> 7914 | F52: =F50*(1-F51) -> 8824.5 | G52: =G50*(1-G51) -> 9757.5 | H52: =H50*(1-H51) -> 10082.25 | I52: =I50*(1-I51) -> 10116
B54: Reinvestment | F54: =SUM(F47:F48) -> 2079 | G54: =SUM(G47:G48) -> 2237 | H54: =SUM(H47:H48) -> -79 | I54: =SUM(I47:I48) -> -148
A56: # | B56: Reinvestment Rate | F56: =F54/F52 -> 0.23559408 | G56: =G54/G52 -> 0.22925954 | H56: =H54/H52 -> -0.0078355526 | I56: =I54/I52 -> -0.014630289
G58: 4 Year Average | I58: =AVERAGE(F56:I56) -> 0.11059695
G59: 4 Year Median | I59: =MEDIAN(F56:I56) -> 0.110712
B62: Calculation of Growth Rate | E62: ='RAW FS'!J$4 -> 44256 | F62: ='RAW FS'!K$4 -> 44621 | G62: ='RAW FS'!L$4 -> 44986 | H62: ='RAW FS'!M$4 -> 45352 | I62: ='RAW FS'!N$4 -> 45717
B64: Reinvestment Rate | F64: =F56 -> 0.23559408 | G64: =G56 -> 0.22925954 | H64: =H56 -> -0.0078355526 | I64: =I56 -> -0.014630289
B65: ROIC | F65: =F42 -> 0.21990057 | G65: =G42 -> 0.2262648 | H65: =H42 -> 0.22912512 | I65: =I42 -> 0.22746897
A66: # | B66: Intrinsic Growth Rate | F66: =F64*F65 -> 0.051807274 | G66: =G64*G65 -> 0.051873366 | H66: =H64*H65 -> -0.0017953219 | I66: =I64*I65 -> -0.0033279367
G68: 4 Year Average | I68: =AVERAGE(F66:I66) -> 0.024639345
G69: 4 Year Median | I69: =MEDIAN(F66:I66) -> 0.025005976

Sheet Financials >

Sheet Historicals
B2: HINDUSTAN UNILEVER
B6: ="Historical Financial Statement " &'Data Sheet'!B1 -> Historical Financial Statement HINDUSTAN UNILEVER LTD
B7: Years | C7: ='Data Sheet'!B16 -> 42460 | D7: ='Data Sheet'!C16 -> 42825 | E7: ='Data Sheet'!D16 -> 43190 | F7: ='Data Sheet'!E16 -> 43555 | G7: ='Data Sheet'!F16 -> 43921 | H7: ='Data Sheet'!G16 -> 44286 | I7: ='Data Sheet'!H16 -> 44651 | J7: ='Data Sheet'!I16 -> 45016 | ... L7: ='Data Sheet'!K16 -> 45747 | M7: LTM
A9: # | B9: Income Statement
B10: Sales | C10: =IFERROR('Data Sheet'!B17,0) -> 32186 | D10: =IFERROR('Data Sheet'!C17,0) -> 33162 | E10: =IFERROR('Data Sheet'!D17,0) -> 35545 | F10: =IFERROR('Data Sheet'!E17,0) -> 39310 | G10: =IFERROR('Data Sheet'!F17,0) -> 39783 | H10: =IFERROR('Data Sheet'!G17,0) -> 47028 | I10: =IFERROR('Data Sheet'!H17,0) -> 52446 | J10: =IFERROR('Data Sheet'!I17,0) -> 60580 | ... L10: =IFERROR('Data Sheet'!K17,0) -> 63121 | M10: =IFERROR(SUM('Data Sheet'!H42:K42),0) -> 64544
B11: Sales Growth | D11: =IFERROR((D10/C10-1),0) -> 0.030323743 | E11: =IFERROR((E10/D10-1),0) -> 0.071859357 | F11: =IFERROR((F10/E10-1),0) -> 0.10592207 | G11: =IFERROR((G10/F10-1),0) -> 0.012032562 | H11: =IFERROR((H10/G10-1),0) -> 0.18211296 | I11: =IFERROR((I10/H10-1),0) -> 0.11520796 | J11: =IFERROR((J10/I10-1),0) -> 0.15509286 | K11: =IFERROR((K10/J10-1),0) -> 0.021723341 | ... M11: =IFERROR((M10/L10-1),0) -> 0.022544003
B13: COGS | C13: =IFERROR(SUM('Data Sheet'!B18,'Data Sheet'!B20:B22,-1*('Data Sheet'!B19)),0) -> 18222 | D13: =IFERROR(SUM('Data Sheet'!C18,'Data Sheet'!C20:C22,-1*('Data Sheet'!C19)),0) -> 18675 | E13: =IFERROR(SUM('Data Sheet'!D18,'Data Sheet'!D20:D22,-1*('Data Sheet'!D19)),0) -> 19314 | F13: =IFERROR(SUM('Data Sheet'!E18,'Data Sheet'!E20:E22,-1*('Data Sheet'!E19)),0) -> 21081 | G13: =IFERROR(SUM('Data Sheet'!F18,'Data Sheet'!F20:F22,-1*('Data Sheet'!F19)),0) -> 20614 | H13: =IFERROR(SUM('Data Sheet'!G18,'Data Sheet'!G20:G22,-1*('Data Sheet'!G19)),0) -> 25301 | I13: =IFERROR(SUM('Data Sheet'!H18,'Data Sheet'!H20:H22,-1*('Data Sheet'!H19)),0) -> 29066 | J13: =IFERROR(SUM('Data Sheet'!I18,'Data Sheet'!I20:I22,-1*('Data Sheet'!I19)),0) -> 35381 | ... M13: =IFERROR(SUM('Data Sheet'!L18,'Data Sheet'!L20:L22,-1*('Data Sheet'!L19)),0) -> 0
B14: COGS % SALES | C14: =IFERROR(C13/C10,0) -> 0.56614677 | D14: =IFERROR(D13/D10,0) -> 0.56314456 | E14: =IFERROR(E13/E10,0) -> 0.54336756 | F14: =IFERROR(F13/F10,0) -> 0.53627576 | G14: =IFERROR(G13/G10,0) -> 0.51816102 | H14: =IFERROR(H13/H10,0) -> 0.53799864 | I14: =IFERROR(I13/I10,0) -> 0.55420814 | J14: =IFERROR(J13/J10,0) -> 0.58403764 | ... M14: =IFERROR(M13/M10,0) -> 0
B16: GROSS PROFIT | C16: =IFERROR(C10-C13,0) -> 13964 | D16: =IFERROR(D10-D13,0) -> 14487 | E16: =IFERROR(E10-E13,0) -> 16231 | F16: =IFERROR(F10-F13,0) -> 18229 | G16: =IFERROR(G10-G13,0) -> 19169 | H16: =IFERROR(H10-H13,0) -> 21727 | I16: =IFERROR(I10-I13,0) -> 23380 | J16: =IFERROR(J10-J13,0) -> 25199 | ... M16: =IFERROR(M10-M13,0) -> 64544
B17: GROSS MARGIN | C17: =C16/C10 -> 0.43385323 | D17: =D16/D10 -> 0.43685544 | E17: =E16/E10 -> 0.45663244 | F17: =F16/F10 -> 0.46372424 | G17: =G16/G10 -> 0.48183898 | H17: =H16/H10 -> 0.46200136 | I17: =I16/I10 -> 0.44579186 | J17: =J16/J10 -> 0.41596236 | ... M17: =M16/M10 -> 1
B19: SALES AND ADMISTRATIVE EXPENSES | C19: =IFERROR(SUM('Data Sheet'!B23:B24),0) -> 8054 | D19: =IFERROR(SUM('Data Sheet'!C23:C24),0) -> 8159 | E19: =IFERROR(SUM('Data Sheet'!D23:D24),0) -> 8732 | F19: =IFERROR(SUM('Data Sheet'!E23:E24),0) -> 9349 | G19: =IFERROR(SUM('Data Sheet'!F23:F24),0) -> 9308 | H19: =IFERROR(SUM('Data Sheet'!G23:G24),0) -> 10101 | I19: =IFERROR(SUM('Data Sheet'!H23:H24),0) -> 10523 | J19: =IFERROR(SUM('Data Sheet'!I23:I24),0) -> 11052 | ... M19: =IFERROR(SUM('Data Sheet'!L23:L24),0) -> 0
B20: S&A EXP % SALES | C20: =C19/C10 -> 0.25023302 | D20: =D19/D10 -> 0.24603462 | E20: =E19/E10 -> 0.24566043 | F20: =F19/F10 -> 0.23782752 | G20: =G19/G10 -> 0.23396928 | H20: =H19/H10 -> 0.21478694 | I20: =I19/I10 -> 0.20064447 | J20: =J19/J10 -> 0.18243645 | ... M20: =M19/M10 -> 0
B22: EBITDA | C22: =IFERROR(C16-C19,0) -> 5910 | D22: =IFERROR(D16-D19,0) -> 6328 | E22: =IFERROR(E16-E19,0) -> 7499 | F22: =IFERROR(F16-F19,0) -> 8880 | G22: =IFERROR(G16-G19,0) -> 9861 | H22: =IFERROR(H16-H19,0) -> 11626 | I22: =IFERROR(I16-I19,0) -> 12857 | J22: =IFERROR(J16-J19,0) -> 14147 | ... M22: =IFERROR(M16-M19,0) -> 64544
B23: EBITDA MARGIN | C23: =C22/C10 -> 0.18362021 | D23: =D22/D10 -> 0.19082082 | E23: =E22/E10 -> 0.21097201 | F23: =F22/F10 -> 0.22589672 | G23: =G22/G10 -> 0.24786969 | H23: =H22/H10 -> 0.24721443 | I23: =I22/I10 -> 0.24514739 | J23: =J22/J10 -> 0.23352592 | ... M23: =M22/M10 -> 1
B25: INTEREST | C25: =IFERROR('Data Sheet'!B27,0) -> 17 | D25: =IFERROR('Data Sheet'!C27,0) -> 35 | E25: =IFERROR('Data Sheet'!D27,0) -> 26 | F25: =IFERROR('Data Sheet'!E27,0) -> 33 | G25: =IFERROR('Data Sheet'!F27,0) -> 118 | H25: =IFERROR('Data Sheet'!G27,0) -> 117 | I25: =IFERROR('Data Sheet'!H27,0) -> 106 | J25: =IFERROR('Data Sheet'!I27,0) -> 114 | ... L25: =IFERROR('Data Sheet'!K27,0) -> 395 | M25: =IFERROR(SUM('Data Sheet'!H46:K46),0) -> 419
B26: INTEREST % SALES | C26: =C25/C10 -> 0.00052817995 | D26: =D25/D10 -> 0.0010554249 | E26: =E25/E10 -> 0.00073146715 | F26: =F25/F10 -> 0.00083948105 | G26: =G25/G10 -> 0.002966091 | H26: =H25/H10 -> 0.0024878796 | I26: =I25/I10 -> 0.0020211265 | J26: =J25/J10 -> 0.0018818092 | ... M26: =M25/M10 -> 0.0064916956
B28: DEPRICIATION | C28: =IFERROR('Data Sheet'!B26,0) -> 353 | D28: =IFERROR('Data Sheet'!C26,0) -> 432 | E28: =IFERROR('Data Sheet'!D26,0) -> 520 | F28: =IFERROR('Data Sheet'!E26,0) -> 565 | G28: =IFERROR('Data Sheet'!F26,0) -> 1002 | H28: =IFERROR('Data Sheet'!G26,0) -> 1074 | I28: =IFERROR('Data Sheet'!H26,0) -> 1091 | J28: =IFERROR('Data Sheet'!I26,0) -> 1137 | ... L28: =IFERROR('Data Sheet'!K26,0) -> 1355 | M28: =IFERROR(SUM('Data Sheet'!H45:K45),0) -> 1367
B29: DEPRICIATION % SALES | C29: =C28/C10 -> 0.010967501 | D29: =D28/D10 -> 0.013026959 | E29: =E28/E10 -> 0.014629343 | F29: =F28/F10 -> 0.014372933 | G29: =G28/G10 -> 0.025186638 | H29: =H28/H10 -> 0.022837459 | I29: =I28/I10 -> 0.020802349 | J29: =J28/J10 -> 0.01876857 | ... M29: =M28/M10 -> 0.021179351
B31: PROFIT BEFORE TAX | C31: =IFERROR(C22-SUM(C25,C28),0) -> 5540 | D31: =IFERROR(D22-SUM(D25,D28),0) -> 5861 | E31: =IFERROR(E22-SUM(E25,E28),0) -> 6953 | F31: =IFERROR(F22-SUM(F25,F28),0) -> 8282 | G31: =IFERROR(G22-SUM(G25,G28),0) -> 8741 | H31: =IFERROR(H22-SUM(H25,H28),0) -> 10435 | I31: =IFERROR(I22-SUM(I25,I28),0) -> 11660 | J31: =IFERROR(J22-SUM(J25,J28),0) -> 12896 | ... M31: =IFERROR(M22-SUM(M25,M28),0) -> 62758
B32: PBT MARGIN | C32: =C31/C10 -> 0.17212453 | D32: =D31/D10 -> 0.17673844 | E32: =E31/E10 -> 0.1956112 | F32: =F31/F10 -> 0.2106843 | G32: =G31/G10 -> 0.21971696 | H32: =H31/H10 -> 0.22188909 | I32: =I31/I10 -> 0.22232391 | J32: =J31/J10 -> 0.21287554 | ... M32: =M31/M10 -> 0.97232895
B34: TAX PAID | C34: =IFERROR('Data Sheet'!B29,0) -> 1875 | D34: =IFERROR('Data Sheet'!C29,0) -> 1977 | E34: =IFERROR('Data Sheet'!D29,0) -> 2079 | F34: =IFERROR('Data Sheet'!E29,0) -> 2544 | G34: =IFERROR('Data Sheet'!F29,0) -> 2409 | H34: =IFERROR('Data Sheet'!G29,0) -> 2606 | I34: =IFERROR('Data Sheet'!H29,0) -> 2987 | J34: =IFERROR('Data Sheet'!I29,0) -> 3201 | ... L34: =IFERROR('Data Sheet'!K29,0) -> 3744 | M34: =IFERROR(SUM('Data Sheet'!H48:K48),0) -> 3134
B35: EFFECTIVE TAX RATE | C35: =C34/C31 -> 0.33844765 | D35: =D34/D31 -> 0.33731445 | E35: =E34/E31 -> 0.29900762 | F35: =F34/F31 -> 0.30717218 | G35: =G34/G31 -> 0.27559776 | H35: =H34/H31 -> 0.24973646 | I35: =I34/I31 -> 0.25617496 | J35: =J34/J31 -> 0.2482165 | ... M35: =M34/M31 -> 0.049937857
B37: NET PROFIT | C37: =C31-C34 -> 3665 | D37: =D31-D34 -> 3884 | E37: =E31-E34 -> 4874 | F37: =F31-F34 -> 5738 | G37: =G31-G34 -> 6332 | H37: =H31-H34 -> 7829 | I37: =I31-I34 -> 8673 | J37: =J31-J34 -> 9695 | ... M37: =M31-M34 -> 59624
B38: NP MARGIN | C38: =C37/C10 -> 0.11386938 | D38: =D37/D10 -> 0.11712201 | E38: =E37/E10 -> 0.13712196 | F38: =F37/F10 -> 0.14596795 | G38: =G37/G10 -> 0.15916346 | H38: =H37/H10 -> 0.16647529 | I38: =I37/I10 -> 0.16537009 | J38: =J37/J10 -> 0.16003632 | ... M38: =M37/M10 -> 0.92377293
B40: No. of Equity Shares | C40: ='Data Sheet'!B93 -> 216.39 | D40: ='Data Sheet'!C93 -> 216.43 | E40: ='Data Sheet'!D93 -> 216.45 | F40: ='Data Sheet'!E93 -> 216.47 | G40: ='Data Sheet'!F93 -> 216.48 | H40: ='Data Sheet'!G93 -> 234.96 | I40: ='Data Sheet'!H93 -> 234.96 | J40: ='Data Sheet'!I93 -> 234.96 | ... L40: ='Data Sheet'!K93 -> 234.96 | M40: =L40 -> 234.96
B42: EPS | C42: =IFERROR(C37/C40,0) -> 16.937012 | D42: =IFERROR(D37/D40,0) -> 17.945756 | E42: =IFERROR(E37/E40,0) -> 22.517903 | F42: =IFERROR(F37/F40,0) -> 26.507137 | G42: =IFERROR(G37/G40,0) -> 29.249815 | H42: =IFERROR(H37/H40,0) -> 33.320565 | I42: =IFERROR(I37/I40,0) -> 36.912666 | J42: =IFERROR(J37/J40,0) -> 41.262343 | ... M42: =IFERROR(M37/M40,0) -> 253.76234
B43: EPS % growth | D43: =IFERROR(D42/C42-1,0) -> 0.059558573 | E43: =IFERROR(E42/D42-1,0) -> 0.25477591 | F43: =IFERROR(F42/E42-1,0) -> 0.17715836 | G43: =IFERROR(G42/F42-1,0) -> 0.10346941 | H43: =IFERROR(H42/G42-1,0) -> 0.13917182 | I43: =IFERROR(I42/H42-1,0) -> 0.10780432 | J43: =IFERROR(J42/I42-1,0) -> 0.11783697 | K43: =IFERROR(K42/J42-1,0) -> -0.023723569 | ... M43: =IFERROR(M42/L42-1,0) -> 5.3775805
B45: DIVIDEND PER SHARE | C45: =IFERROR('Data Sheet'!B31/Historicals!C40,0) -> 15.971163 | D45: =IFERROR('Data Sheet'!C31/Historicals!D40,0) -> 16.966225 | E45: =IFERROR('Data Sheet'!D31/Historicals!E40,0) -> 19.95842 | F45: =IFERROR('Data Sheet'!E31/Historicals!F40,0) -> 21.952234 | G45: =IFERROR('Data Sheet'!F31/Historicals!G40,0) -> 24.944568 | H45: =IFERROR('Data Sheet'!G31/Historicals!H40,0) -> 40.506895 | I45: =IFERROR('Data Sheet'!H31/Historicals!I40,0) -> 34.005788 | J45: =IFERROR('Data Sheet'!I31/Historicals!J40,0) -> 39.006639 | ... M45: =IFERROR('Data Sheet'!L31/Historicals!M40,0) -> 0
B46: DIVIDEND PAYOUT RATIO | C46: =C45/C42 -> 0.94297408 | D46: =D45/D42 -> 0.9454171 | E46: =E45/E42 -> 0.88633566 | F46: =F45/F42 -> 0.82816312 | G46: =G45/G42 -> 0.85281112 | H46: =H45/H42 -> 1.2156725 | I46: =I45/I42 -> 0.92124986 | J46: =J45/J42 -> 0.94533265 | ... M46: =M45/M42 -> 0
B48: RETAINED EARNINGS | C48: =1-C46 -> 0.057025921 | D48: =1-D46 -> 0.054582904 | E48: =1-E46 -> 0.11366434 | F48: =1-F46 -> 0.17183688 | G48: =1-G46 -> 0.14718888 | H48: =1-H46 -> -0.2156725 | I48: =1-I46 -> 0.078750144 | J48: =1-J46 -> 0.054667354 | ... M48: =1-M46 -> 1
A51: # | B51: Balance Sheet
B53: Equity Share Capital | C53: =IFERROR('Data Sheet'!B57,0) -> 216 | D53: =IFERROR('Data Sheet'!C57,0) -> 216 | E53: =IFERROR('Data Sheet'!D57,0) -> 216 | F53: =IFERROR('Data Sheet'!E57,0) -> 216 | G53: =IFERROR('Data Sheet'!F57,0) -> 216 | H53: =IFERROR('Data Sheet'!G57,0) -> 235 | I53: =IFERROR('Data Sheet'!H57,0) -> 235 | J53: =IFERROR('Data Sheet'!I57,0) -> 235 | ... L53: =IFERROR('Data Sheet'!K57,0) -> 235
B54: Reserves | C54: =IFERROR('Data Sheet'!B58,0) -> 6357 | D54: =IFERROR('Data Sheet'!C58,0) -> 6528 | E54: =IFERROR('Data Sheet'!D58,0) -> 7065 | F54: =IFERROR('Data Sheet'!E58,0) -> 7651 | G54: =IFERROR('Data Sheet'!F58,0) -> 8013 | H54: =IFERROR('Data Sheet'!G58,0) -> 47439 | I54: =IFERROR('Data Sheet'!H58,0) -> 48826 | J54: =IFERROR('Data Sheet'!I58,0) -> 50069 | ... L54: =IFERROR('Data Sheet'!K58,0) -> 49167
B55: Borrowings | C55: =IFERROR('Data Sheet'!B59,0) -> 177 | D55: =IFERROR('Data Sheet'!C59,0) -> 277 | E55: =IFERROR('Data Sheet'!D59,0) -> 0 | F55: =IFERROR('Data Sheet'!E59,0) -> 99 | G55: =IFERROR('Data Sheet'!F59,0) -> 0 | H55: =IFERROR('Data Sheet'!G59,0) -> 0 | I55: =IFERROR('Data Sheet'!H59,0) -> 1043 | J55: =IFERROR('Data Sheet'!I59,0) -> 1219 | ... L55: =IFERROR('Data Sheet'!K59,0) -> 1648
B56: Other Liabilities | C56: =IFERROR('Data Sheet'!B60,0) -> 8043 | D56: =IFERROR('Data Sheet'!C60,0) -> 8685 | E56: =IFERROR('Data Sheet'!D60,0) -> 10581 | F56: =IFERROR('Data Sheet'!E60,0) -> 10663 | G56: =IFERROR('Data Sheet'!F60,0) -> 11924 | H56: =IFERROR('Data Sheet'!G60,0) -> 21066 | I56: =IFERROR('Data Sheet'!H60,0) -> 20402 | J56: =IFERROR('Data Sheet'!I60,0) -> 21554 | ... L56: =IFERROR('Data Sheet'!K60,0) -> 28813
B57: Total | C57: =IFERROR('Data Sheet'!B61,0) -> 14793 | D57: =IFERROR('Data Sheet'!C61,0) -> 15706 | E57: =IFERROR('Data Sheet'!D61,0) -> 17862 | F57: =IFERROR('Data Sheet'!E61,0) -> 18629 | G57: =IFERROR('Data Sheet'!F61,0) -> 20153 | H57: =IFERROR('Data Sheet'!G61,0) -> 68740 | I57: =IFERROR('Data Sheet'!H61,0) -> 70506 | J57: =IFERROR('Data Sheet'!I61,0) -> 73077 | ... L57: =IFERROR('Data Sheet'!K61,0) -> 79863
B59: Fixed Assets Net Block | C59: =IFERROR('Data Sheet'!B62,0) -> 3258 | D59: =IFERROR('Data Sheet'!C62,0) -> 4419 | E59: =IFERROR('Data Sheet'!D62,0) -> 4528 | F59: =IFERROR('Data Sheet'!E62,0) -> 4715 | G59: =IFERROR('Data Sheet'!F62,0) -> 5479 | H59: =IFERROR('Data Sheet'!G62,0) -> 51443 | I59: =IFERROR('Data Sheet'!H62,0) -> 51473 | J59: =IFERROR('Data Sheet'!I62,0) -> 52678 | ... L59: =IFERROR('Data Sheet'!K62,0) -> 54335
B60: Capital Work in Progress | C60: =IFERROR('Data Sheet'!B63,0) -> 408 | D60: =IFERROR('Data Sheet'!C63,0) -> 229 | E60: =IFERROR('Data Sheet'!D63,0) -> 461 | F60: =IFERROR('Data Sheet'!E63,0) -> 406 | G60: =IFERROR('Data Sheet'!F63,0) -> 597 | H60: =IFERROR('Data Sheet'!G63,0) -> 745 | I60: =IFERROR('Data Sheet'!H63,0) -> 1313 | J60: =IFERROR('Data Sheet'!I63,0) -> 1132 | ... L60: =IFERROR('Data Sheet'!K63,0) -> 1009
B61: Investments | C61: =IFERROR('Data Sheet'!B64,0) -> 2592 | D61: =IFERROR('Data Sheet'!C64,0) -> 3794 | E61: =IFERROR('Data Sheet'!D64,0) -> 2873 | F61: =IFERROR('Data Sheet'!E64,0) -> 2716 | G61: =IFERROR('Data Sheet'!F64,0) -> 1255 | H61: =IFERROR('Data Sheet'!G64,0) -> 2709 | I61: =IFERROR('Data Sheet'!H64,0) -> 3521 | J61: =IFERROR('Data Sheet'!I64,0) -> 2882 | ... L61: =IFERROR('Data Sheet'!K64,0) -> 3810
B62: Other Assets | C62: =IFERROR('Data Sheet'!B65-SUM(C65:C67),0) -> 1536 | D62: =IFERROR('Data Sheet'!C65-SUM(D65:D67),0) -> 1810 | E62: =IFERROR('Data Sheet'!D65-SUM(E65:E67),0) -> 2692 | F62: =IFERROR('Data Sheet'!E65-SUM(F65:F67),0) -> 2645 | G62: =IFERROR('Data Sheet'!F65-SUM(G65:G67),0) -> 3793 | H62: =IFERROR('Data Sheet'!G65-SUM(H65:H67),0) -> 4035 | I62: =IFERROR('Data Sheet'!H65-SUM(I65:I67),0) -> 4021 | J62: =IFERROR('Data Sheet'!I65-SUM(J65:J67),0) -> 4377 | ... L62: =IFERROR('Data Sheet'!K65-SUM(L65:L67),0) -> 4921
B63: Total Non-Current Assets | C63: =IFERROR(SUM(C59:C62),0) -> 7794 | D63: =IFERROR(SUM(D59:D62),0) -> 10252 | E63: =IFERROR(SUM(E59:E62),0) -> 10554 | F63: =IFERROR(SUM(F59:F62),0) -> 10482 | G63: =IFERROR(SUM(G59:G62),0) -> 11124 | H63: =IFERROR(SUM(H59:H62),0) -> 58932 | I63: =IFERROR(SUM(I59:I62),0) -> 60328 | J63: =IFERROR(SUM(J59:J62),0) -> 61069 | ... L63: =IFERROR(SUM(L59:L62),0) -> 64075
B65: Receivables | C65: =IFERROR('Data Sheet'!B67,0) -> 1264 | D65: =IFERROR('Data Sheet'!C67,0) -> 1085 | E65: =IFERROR('Data Sheet'!D67,0) -> 1310 | F65: =IFERROR('Data Sheet'!E67,0) -> 1816 | G65: =IFERROR('Data Sheet'!F67,0) -> 1149 | H65: =IFERROR('Data Sheet'!G67,0) -> 1758 | I65: =IFERROR('Data Sheet'!H67,0) -> 2236 | J65: =IFERROR('Data Sheet'!I67,0) -> 3079 | ... L65: =IFERROR('Data Sheet'!K67,0) -> 3819
B66: Inventory | C66: =IFERROR('Data Sheet'!B68,0) -> 2726 | D66: =IFERROR('Data Sheet'!C68,0) -> 2541 | E66: =IFERROR('Data Sheet'!D68,0) -> 2513 | F66: =IFERROR('Data Sheet'!E68,0) -> 2574 | G66: =IFERROR('Data Sheet'!F68,0) -> 2767 | H66: =IFERROR('Data Sheet'!G68,0) -> 3579 | I66: =IFERROR('Data Sheet'!H68,0) -> 4096 | J66: =IFERROR('Data Sheet'!I68,0) -> 4251 | ... L66: =IFERROR('Data Sheet'!K68,0) -> 4415
B67: Cash & Bank | C67: =IFERROR('Data Sheet'!B69,0) -> 3009 | D67: =IFERROR('Data Sheet'!C69,0) -> 1828 | E67: =IFERROR('Data Sheet'!D69,0) -> 3485 | F67: =IFERROR('Data Sheet'!E69,0) -> 3757 | G67: =IFERROR('Data Sheet'!F69,0) -> 5113 | H67: =IFERROR('Data Sheet'!G69,0) -> 4471 | I67: =IFERROR('Data Sheet'!H69,0) -> 3846 | J67: =IFERROR('Data Sheet'!I69,0) -> 4678 | ... L67: =IFERROR('Data Sheet'!K69,0) -> 7554
B68: Total Current Assets | C68: =IFERROR(SUM(C65:C67),0) -> 6999 | D68: =IFERROR(SUM(D65:D67),0) -> 5454 | E68: =IFERROR(SUM(E65:E67),0) -> 7308 | F68: =IFERROR(SUM(F65:F67),0) -> 8147 | G68: =IFERROR(SUM(G65:G67),0) -> 9029 | H68: =IFERROR(SUM(H65:H67),0) -> 9808 | I68: =IFERROR(SUM(I65:I67),0) -> 10178 | J68: =IFERROR(SUM(J65:J67),0) -> 12008 | ... L68: =IFERROR(SUM(L65:L67),0) -> 15788
B70: Total Assets | C70: =IFERROR(C63+C68,0) -> 14793 | D70: =IFERROR(D63+D68,0) -> 15706 | E70: =IFERROR(E63+E68,0) -> 17862 | F70: =IFERROR(F63+F68,0) -> 18629 | G70: =IFERROR(G63+G68,0) -> 20153 | H70: =IFERROR(H63+H68,0) -> 68740 | I70: =IFERROR(I63+I68,0) -> 70506 | J70: =IFERROR(J63+J68,0) -> 73077 | ... L70: =IFERROR(L63+L68,0) -> 79863
B72: CHECK | C72: =C70=C57 -> TRUE | D72: =D70=D57 -> TRUE | E72: =E70=E57 -> TRUE | F72: =F70=F57 -> TRUE | G72: =G70=G57 -> TRUE | H72: =H70=H57 -> TRUE | I72: =I70=I57 -> TRUE | J72: =J70=J57 -> TRUE | ... L72: =L70=L57 -> TRUE
B74: No. of Equity Shares | C74: =IFERROR('Data Sheet'!B70/10000000,0) -> 216.3937 | D74: =IFERROR('Data Sheet'!C70/10000000,0) -> 216.43496 | E74: =IFERROR('Data Sheet'!D70/10000000,0) -> 216.45288 | F74: =IFERROR('Data Sheet'!E70/10000000,0) -> 216.47044 | G74: =IFERROR('Data Sheet'!F70/10000000,0) -> 216.47044 | H74: =IFERROR('Data Sheet'!G70/10000000,0) -> 234.95678 | I74: =IFERROR('Data Sheet'!H70/10000000,0) -> 234.95913 | J74: =IFERROR('Data Sheet'!I70/10000000,0) -> 234.95913 | ... L74: =IFERROR('Data Sheet'!K70/10000000,0) -> 234.95913
B75: New Bonus Shares | C75: =IFERROR('Data Sheet'!B71,0) -> 0 | D75: =IFERROR('Data Sheet'!C71,0) -> 0 | E75: =IFERROR('Data Sheet'!D71,0) -> 0 | F75: =IFERROR('Data Sheet'!E71,0) -> 0 | G75: =IFERROR('Data Sheet'!F71,0) -> 0 | H75: =IFERROR('Data Sheet'!G71,0) -> 0 | I75: =IFERROR('Data Sheet'!H71,0) -> 0 | J75: =IFERROR('Data Sheet'!I71,0) -> 0 | ... L75: =IFERROR('Data Sheet'!K71,0) -> 0
B76: Face value | C76: =IFERROR('Data Sheet'!B72,0) -> 1 | D76: =IFERROR('Data Sheet'!C72,0) -> 1 | E76: =IFERROR('Data Sheet'!D72,0) -> 1 | F76: =IFERROR('Data Sheet'!E72,0) -> 1 | G76: =IFERROR('Data Sheet'!F72,0) -> 1 | H76: =IFERROR('Data Sheet'!G72,0) -> 1 | I76: =IFERROR('Data Sheet'!H72,0) -> 1 | J76: =IFERROR('Data Sheet'!I72,0) -> 1 | ... L76: =IFERROR('Data Sheet'!K72,0) -> 1
A78: # | B78: Cash Flow Statement
B79: Operating Activity
B80: Profit from operations | C80: =IFERROR('Cash Flow Data'!E4,0) -> 6025 | D80: =IFERROR('Cash Flow Data'!F4,0) -> 6512 | E80: =IFERROR('Cash Flow Data'!G4,0) -> 7485 | F80: =IFERROR('Cash Flow Data'!H4,0) -> 8909 | G80: =IFERROR('Cash Flow Data'!I4,0) -> 9723 | H80: =IFERROR('Cash Flow Data'!J4,0) -> 11672 | I80: =IFERROR('Cash Flow Data'!K4,0) -> 12829 | J80: =IFERROR('Cash Flow Data'!L4,0) -> 14089 | ... L80: =IFERROR('Cash Flow Data'!N4,0) -> 14942
B81: Receivables | C81: =IFERROR('Cash Flow Data'!E5,0) -> -257 | D81: =IFERROR('Cash Flow Data'!F5,0) -> 173 | E81: =IFERROR('Cash Flow Data'!G5,0) -> 0 | F81: =IFERROR('Cash Flow Data'!H5,0) -> 0 | G81: =IFERROR('Cash Flow Data'!I5,0) -> 0 | H81: =IFERROR('Cash Flow Data'!J5,0) -> 0 | I81: =IFERROR('Cash Flow Data'!K5,0) -> 0 | J81: =IFERROR('Cash Flow Data'!L5,0) -> 0 | ... L81: =IFERROR('Cash Flow Data'!N5,0) -> 0
B82: Inventory | C82: =IFERROR('Cash Flow Data'!E6,0) -> 89 | D82: =IFERROR('Cash Flow Data'!F6,0) -> 37 | E82: =IFERROR('Cash Flow Data'!G6,0) -> -146 | F82: =IFERROR('Cash Flow Data'!H6,0) -> -195 | G82: =IFERROR('Cash Flow Data'!I6,0) -> -331 | H82: =IFERROR('Cash Flow Data'!J6,0) -> -543 | I82: =IFERROR('Cash Flow Data'!K6,0) -> -758 | J82: =IFERROR('Cash Flow Data'!L6,0) -> -339 | ... L82: =IFERROR('Cash Flow Data'!N6,0) -> -584
B83: Payables | C83: =IFERROR('Cash Flow Data'!E7,0) -> 164 | D83: =IFERROR('Cash Flow Data'!F7,0) -> 501 | E83: =IFERROR('Cash Flow Data'!G7,0) -> 0 | F83: =IFERROR('Cash Flow Data'!H7,0) -> 0 | G83: =IFERROR('Cash Flow Data'!I7,0) -> 0 | H83: =IFERROR('Cash Flow Data'!J7,0) -> 0 | I83: =IFERROR('Cash Flow Data'!K7,0) -> 0 | J83: =IFERROR('Cash Flow Data'!L7,0) -> 0 | ... L83: =IFERROR('Cash Flow Data'!N7,0) -> 0
B84: Other WC items | C84: =IFERROR(SUM('Cash Flow Data'!E8:E10),0) -> -77 | D84: =IFERROR(SUM('Cash Flow Data'!F8:F10),0) -> -145 | E84: =IFERROR(SUM('Cash Flow Data'!G8:G10),0) -> 982 | F84: =IFERROR(SUM('Cash Flow Data'!H8:H10),0) -> -147 | G84: =IFERROR(SUM('Cash Flow Data'!I8:I10),0) -> 742 | H84: =IFERROR(SUM('Cash Flow Data'!J8:J10),0) -> 442 | I84: =IFERROR(SUM('Cash Flow Data'!K8:K10),0) -> -242 | J84: =IFERROR(SUM('Cash Flow Data'!L8:L10),0) -> -621 | ... L84: =IFERROR(SUM('Cash Flow Data'!N8:N10),0) -> -204
B85: Working capital changes | C85: =IFERROR(SUM(C81:C84),0) -> -81 | D85: =IFERROR(SUM(D81:D84),0) -> 566 | E85: =IFERROR(SUM(E81:E84),0) -> 836 | F85: =IFERROR(SUM(F81:F84),0) -> -342 | G85: =IFERROR(SUM(G81:G84),0) -> 411 | H85: =IFERROR(SUM(H81:H84),0) -> -101 | I85: =IFERROR(SUM(I81:I84),0) -> -1000 | J85: =IFERROR(SUM(J81:J84),0) -> -960 | ... L85: =IFERROR(SUM(L81:L84),0) -> -788
B86: Direct taxes | C86: =IFERROR('Cash Flow Data'!E12,0) -> -1765 | D86: =IFERROR('Cash Flow Data'!F12,0) -> -1859 | E86: =IFERROR('Cash Flow Data'!G12,0) -> -2264 | F86: =IFERROR('Cash Flow Data'!H12,0) -> -2767 | G86: =IFERROR('Cash Flow Data'!I12,0) -> -2505 | H86: =IFERROR('Cash Flow Data'!J12,0) -> -2407 | I86: =IFERROR('Cash Flow Data'!K12,0) -> -2784 | J86: =IFERROR('Cash Flow Data'!L12,0) -> -3138 | ... L86: =IFERROR('Cash Flow Data'!N12,0) -> -2268
B87: Other operating items | C87: ='Cash Flow Data'!E13 -> -8 | D87: ='Cash Flow Data'!F13 -> -21 | E87: ='Cash Flow Data'!G13 -> 0 | F87: ='Cash Flow Data'!H13 -> 0 | G87: ='Cash Flow Data'!I13 -> 0 | H87: ='Cash Flow Data'!J13 -> 0 | I87: ='Cash Flow Data'!K13 -> 0 | J87: ='Cash Flow Data'!L13 -> 0 | ... L87: ='Cash Flow Data'!N13 -> 0
B88: Exceptional CF items | C88: ='Cash Flow Data'!E14 -> 0 | D88: ='Cash Flow Data'!F14 -> -13 | E88: ='Cash Flow Data'!G14 -> 2 | F88: ='Cash Flow Data'!H14 -> 0 | G88: ='Cash Flow Data'!I14 -> -6 | H88: ='Cash Flow Data'!J14 -> -1 | I88: ='Cash Flow Data'!K14 -> 3 | J88: ='Cash Flow Data'!L14 -> 0 | ... L88: ='Cash Flow Data'!N14 -> 0
B89: Cash from Operating Activities | C89: =SUM(C80,C85:C88) -> 4171 | D89: =SUM(D80,D85:D88) -> 5185 | E89: =SUM(E80,E85:E88) -> 6059 | F89: =SUM(F80,F85:F88) -> 5800 | G89: =SUM(G80,G85:G88) -> 7623 | H89: =SUM(H80,H85:H88) -> 9163 | I89: =SUM(I80,I85:I88) -> 9048 | J89: =SUM(J80,J85:J88) -> 9991 | ... L89: =SUM(L80,L85:L88) -> 11886
B91: Investing Activity
B92: Fixed assets purchased | C92: =IFERROR('Cash Flow Data'!E16,0) -> -810 | D92: =IFERROR('Cash Flow Data'!F16,0) -> -1113 | E92: =IFERROR('Cash Flow Data'!G16,0) -> -895 | F92: =IFERROR('Cash Flow Data'!H16,0) -> -767 | G92: =IFERROR('Cash Flow Data'!I16,0) -> -862 | H92: =IFERROR('Cash Flow Data'!J16,0) -> -4163 | I92: =IFERROR('Cash Flow Data'!K16,0) -> -1228 | J92: =IFERROR('Cash Flow Data'!L16,0) -> -1192 | ... L92: =IFERROR('Cash Flow Data'!N16,0) -> -1275
B93: Fixed assets sold | C93: =IFERROR('Cash Flow Data'!E17,0) -> 99 | D93: =IFERROR('Cash Flow Data'!F17,0) -> 176 | E93: =IFERROR('Cash Flow Data'!G17,0) -> 32 | F93: =IFERROR('Cash Flow Data'!H17,0) -> 13 | G93: =IFERROR('Cash Flow Data'!I17,0) -> 52 | H93: =IFERROR('Cash Flow Data'!J17,0) -> 97 | I93: =IFERROR('Cash Flow Data'!K17,0) -> 175 | J93: =IFERROR('Cash Flow Data'!L17,0) -> 181 | ... L93: =IFERROR('Cash Flow Data'!N17,0) -> 13
B94: Investments purchased | C94: =IFERROR('Cash Flow Data'!E18,0) -> -20666 | D94: =IFERROR('Cash Flow Data'!F18,0) -> -31214 | E94: =IFERROR('Cash Flow Data'!G18,0) -> -51855 | F94: =IFERROR('Cash Flow Data'!H18,0) -> -74365 | G94: =IFERROR('Cash Flow Data'!I18,0) -> -36090 | H94: =IFERROR('Cash Flow Data'!J18,0) -> -39920 | I94: =IFERROR('Cash Flow Data'!K18,0) -> -48522 | J94: =IFERROR('Cash Flow Data'!L18,0) -> -22649 | ... L94: =IFERROR('Cash Flow Data'!N18,0) -> -22957
B95: Investments sold | C95: =IFERROR('Cash Flow Data'!E19,0) -> 20937 | D95: =IFERROR('Cash Flow Data'!F19,0) -> 30083 | E95: =IFERROR('Cash Flow Data'!G19,0) -> 52897 | F95: =IFERROR('Cash Flow Data'!H19,0) -> 74691 | G95: =IFERROR('Cash Flow Data'!I19,0) -> 37690 | H95: =IFERROR('Cash Flow Data'!J19,0) -> 38486 | I95: =IFERROR('Cash Flow Data'!K19,0) -> 47786 | J95: =IFERROR('Cash Flow Data'!L19,0) -> 23462 | ... L95: =IFERROR('Cash Flow Data'!N19,0) -> 23987
B96: Interest received | C96: =IFERROR('Cash Flow Data'!E20,0) -> 315 | D96: =IFERROR('Cash Flow Data'!F20,0) -> 264 | E96: =IFERROR('Cash Flow Data'!G20,0) -> 297 | F96: =IFERROR('Cash Flow Data'!H20,0) -> 289 | G96: =IFERROR('Cash Flow Data'!I20,0) -> 351 | H96: =IFERROR('Cash Flow Data'!J20,0) -> 277 | I96: =IFERROR('Cash Flow Data'!K20,0) -> 161 | J96: =IFERROR('Cash Flow Data'!L20,0) -> 259 | ... L96: =IFERROR('Cash Flow Data'!N20,0) -> 835
B97: Dividends received | C97: =IFERROR('Cash Flow Data'!E21,0) -> 33 | D97: =IFERROR('Cash Flow Data'!F21,0) -> 14 | E97: =IFERROR('Cash Flow Data'!G21,0) -> 0 | F97: =IFERROR('Cash Flow Data'!H21,0) -> 1 | G97: =IFERROR('Cash Flow Data'!I21,0) -> 1 | H97: =IFERROR('Cash Flow Data'!J21,0) -> 1 | I97: =IFERROR('Cash Flow Data'!K21,0) -> 1 | J97: =IFERROR('Cash Flow Data'!L21,0) -> 2 | ... L97: =IFERROR('Cash Flow Data'!N21,0) -> 0
B98: Invest in subsidiaries | C98: =IFERROR('Cash Flow Data'!E22,0) -> 0 | D98: =IFERROR('Cash Flow Data'!F22,0) -> 0 | E98: =IFERROR('Cash Flow Data'!G22,0) -> 0 | F98: =IFERROR('Cash Flow Data'!H22,0) -> 0 | G98: =IFERROR('Cash Flow Data'!I22,0) -> 0 | H98: =IFERROR('Cash Flow Data'!J22,0) -> 0 | I98: =IFERROR('Cash Flow Data'!K22,0) -> 0 | J98: =IFERROR('Cash Flow Data'!L22,0) -> 0 | ... L98: =IFERROR('Cash Flow Data'!N22,0) -> 0
B99: Loans to subsidiaries | C99: =IFERROR('Cash Flow Data'!E23,0) -> 0 | D99: =IFERROR('Cash Flow Data'!F23,0) -> 0 | E99: =IFERROR('Cash Flow Data'!G23,0) -> 0 | F99: =IFERROR('Cash Flow Data'!H23,0) -> 0 | G99: =IFERROR('Cash Flow Data'!I23,0) -> 0 | H99: =IFERROR('Cash Flow Data'!J23,0) -> 0 | I99: =IFERROR('Cash Flow Data'!K23,0) -> 0 | J99: =IFERROR('Cash Flow Data'!L23,0) -> 0 | ... L99: =IFERROR('Cash Flow Data'!N23,0) -> 0
B100: Redemp n Canc of Shares | C100: =IFERROR('Cash Flow Data'!E24,0) -> 161 | D100: =IFERROR('Cash Flow Data'!F24,0) -> 20 | E100: =IFERROR('Cash Flow Data'!G24,0) -> 73 | F100: =IFERROR('Cash Flow Data'!H24,0) -> 0 | G100: =IFERROR('Cash Flow Data'!I24,0) -> 0 | H100: =IFERROR('Cash Flow Data'!J24,0) -> 0 | I100: =IFERROR('Cash Flow Data'!K24,0) -> 0 | J100: =IFERROR('Cash Flow Data'!L24,0) -> 0 | ... L100: =IFERROR('Cash Flow Data'!N24,0) -> 0
B101: Acquisition of companies | C101: =IFERROR('Cash Flow Data'!E25,0) -> 0 | D101: =IFERROR('Cash Flow Data'!F25,0) -> 0 | E101: =IFERROR('Cash Flow Data'!G25,0) -> 0 | F101: =IFERROR('Cash Flow Data'!H25,0) -> 0 | G101: =IFERROR('Cash Flow Data'!I25,0) -> 0 | H101: =IFERROR('Cash Flow Data'!J25,0) -> 0 | I101: =IFERROR('Cash Flow Data'!K25,0) -> 0 | J101: =IFERROR('Cash Flow Data'!L25,0) -> -334 | ... L101: =IFERROR('Cash Flow Data'!N25,0) -> 0
B102: Other investing items | C102: =IFERROR('Cash Flow Data'!E26,0) -> -351 | D102: =IFERROR('Cash Flow Data'!F26,0) -> 597 | E102: =IFERROR('Cash Flow Data'!G26,0) -> -1612 | F102: =IFERROR('Cash Flow Data'!H26,0) -> -300 | G102: =IFERROR('Cash Flow Data'!I26,0) -> 649 | H102: =IFERROR('Cash Flow Data'!J26,0) -> 3994 | I102: =IFERROR('Cash Flow Data'!K26,0) -> -101 | J102: =IFERROR('Cash Flow Data'!L26,0) -> -1213 | ... L102: =IFERROR('Cash Flow Data'!N26,0) -> 5870
B103: Cash From Investing Activities | C103: =SUM(C92:C102) -> -282 | D103: =SUM(D92:D102) -> -1173 | E103: =SUM(E92:E102) -> -1063 | F103: =SUM(F92:F102) -> -438 | G103: =SUM(G92:G102) -> 1791 | H103: =SUM(H92:H102) -> -1228 | I103: =SUM(I92:I102) -> -1728 | J103: =SUM(J92:J102) -> -1484 | ... L103: =SUM(L92:L102) -> 6473
B105: Financing Activity
B106: Proceeds from shares | C106: =IFERROR('Cash Flow Data'!E28,0) -> 0 | D106: =IFERROR('Cash Flow Data'!F28,0) -> 0 | E106: =IFERROR('Cash Flow Data'!G28,0) -> 0 | F106: =IFERROR('Cash Flow Data'!H28,0) -> 0 | G106: =IFERROR('Cash Flow Data'!I28,0) -> 0 | H106: =IFERROR('Cash Flow Data'!J28,0) -> 0 | I106: =IFERROR('Cash Flow Data'!K28,0) -> 0 | J106: =IFERROR('Cash Flow Data'!L28,0) -> 0 | ... L106: =IFERROR('Cash Flow Data'!N28,0) -> 0
B107: Proceeds from borrowings | C107: =IFERROR('Cash Flow Data'!E29,0) -> 177 | D107: =IFERROR('Cash Flow Data'!F29,0) -> 460 | E107: =IFERROR('Cash Flow Data'!G29,0) -> 0 | F107: =IFERROR('Cash Flow Data'!H29,0) -> 99 | G107: =IFERROR('Cash Flow Data'!I29,0) -> 0 | H107: =IFERROR('Cash Flow Data'!J29,0) -> 188 | I107: =IFERROR('Cash Flow Data'!K29,0) -> 55 | J107: =IFERROR('Cash Flow Data'!L29,0) -> 286 | ... L107: =IFERROR('Cash Flow Data'!N29,0) -> 0
B108: Repayment of borrowings | C108: =IFERROR('Cash Flow Data'!E30,0) -> 0 | D108: =IFERROR('Cash Flow Data'!F30,0) -> -360 | E108: =IFERROR('Cash Flow Data'!G30,0) -> -277 | F108: =IFERROR('Cash Flow Data'!H30,0) -> 0 | G108: =IFERROR('Cash Flow Data'!I30,0) -> -99 | H108: =IFERROR('Cash Flow Data'!J30,0) -> -188 | I108: =IFERROR('Cash Flow Data'!K30,0) -> -55 | J108: =IFERROR('Cash Flow Data'!L30,0) -> -208 | ... L108: =IFERROR('Cash Flow Data'!N30,0) -> 0
B109: Interest paid fin | C109: =IFERROR('Cash Flow Data'!E31,0) -> -2 | D109: =IFERROR('Cash Flow Data'!F31,0) -> -14 | E109: =IFERROR('Cash Flow Data'!G31,0) -> -6 | F109: =IFERROR('Cash Flow Data'!H31,0) -> -7 | G109: =IFERROR('Cash Flow Data'!I31,0) -> -90 | H109: =IFERROR('Cash Flow Data'!J31,0) -> -92 | I109: =IFERROR('Cash Flow Data'!K31,0) -> -82 | J109: =IFERROR('Cash Flow Data'!L31,0) -> -88 | ... L109: =IFERROR('Cash Flow Data'!N31,0) -> -130
B110: Dividends paid | C110: =IFERROR('Cash Flow Data'!E32,0) -> -3354 | D110: =IFERROR('Cash Flow Data'!F32,0) -> -3572 | E110: =IFERROR('Cash Flow Data'!G32,0) -> -3911 | F110: =IFERROR('Cash Flow Data'!H32,0) -> -4554 | G110: =IFERROR('Cash Flow Data'!I32,0) -> -5196 | H110: =IFERROR('Cash Flow Data'!J32,0) -> -8811 | I110: =IFERROR('Cash Flow Data'!K32,0) -> -7526 | J110: =IFERROR('Cash Flow Data'!L32,0) -> -8474 | ... L110: =IFERROR('Cash Flow Data'!N32,0) -> -12473
B111: Financial liabilities | C111: =IFERROR('Cash Flow Data'!E33,0) -> 0 | D111: =IFERROR('Cash Flow Data'!F33,0) -> 0 | E111: =IFERROR('Cash Flow Data'!G33,0) -> 0 | F111: =IFERROR('Cash Flow Data'!H33,0) -> 0 | G111: =IFERROR('Cash Flow Data'!I33,0) -> -373 | H111: =IFERROR('Cash Flow Data'!J33,0) -> -406 | I111: =IFERROR('Cash Flow Data'!K33,0) -> -407 | J111: =IFERROR('Cash Flow Data'!L33,0) -> -467 | ... L111: =IFERROR('Cash Flow Data'!N33,0) -> -498
B112: Other financing items | C112: =IFERROR('Cash Flow Data'!E34,0) -> -685 | D112: =IFERROR('Cash Flow Data'!F34,0) -> -728 | E112: =IFERROR('Cash Flow Data'!G34,0) -> -781 | F112: =IFERROR('Cash Flow Data'!H34,0) -> -928 | G112: =IFERROR('Cash Flow Data'!I34,0) -> -1061 | H112: =IFERROR('Cash Flow Data'!J34,0) -> 0 | I112: =IFERROR('Cash Flow Data'!K34,0) -> 0 | J112: =IFERROR('Cash Flow Data'!L34,0) -> -2 | ... L112: =IFERROR('Cash Flow Data'!N34,0) -> 0
B113: Cash From Financing Activities | C113: =SUM(C106:C112) -> -3864 | D113: =SUM(D106:D112) -> -4214 | E113: =SUM(E106:E112) -> -4975 | F113: =SUM(F106:F112) -> -5390 | G113: =SUM(G106:G112) -> -6819 | H113: =SUM(H106:H112) -> -9309 | I113: =SUM(I106:I112) -> -8015 | J113: =SUM(J106:J112) -> -8953 | ... L113: =SUM(L106:L112) -> -13101
B115: Net Cash Flow | C115: =IFERROR(SUM(C89,C103,C113),0) -> 25 | D115: =IFERROR(SUM(D89,D103,D113),0) -> -202 | E115: =IFERROR(SUM(E89,E103,E113),0) -> 21 | F115: =IFERROR(SUM(F89,F103,F113),0) -> -28 | G115: =IFERROR(SUM(G89,G103,G113),0) -> 2595 | H115: =IFERROR(SUM(H89,H103,H113),0) -> -1374 | I115: =IFERROR(SUM(I89,I103,I113),0) -> -695 | J115: =IFERROR(SUM(J89,J103,J113),0) -> -446 | ... L115: =IFERROR(SUM(L89,L103,L113),0) -> 5258
C117: =C115='Cash Flow Data'!E35 -> TRUE | D117: =D115='Cash Flow Data'!F35 -> TRUE | E117: =E115='Cash Flow Data'!G35 -> TRUE | F117: =F115='Cash Flow Data'!H35 -> TRUE | G117: =G115='Cash Flow Data'!I35 -> TRUE | H117: =H115='Cash Flow Data'!J35 -> TRUE | I117: =I115='Cash Flow Data'!K35 -> TRUE | J117: =J115='Cash Flow Data'!L35 -> TRUE | ... L117: =L115='Cash Flow Data'!N35 -> TRUE

Sheet Common Size
B1: HINDUSTAN UNILEVER
B5: ="Common Size Statement - " &'Data Sheet'!$B$1 -> Common Size Statement - HINDUSTAN UNILEVER LTD
B6: Years | C6: ='Data Sheet'!B16 -> 42460 | D6: ='Data Sheet'!C16 -> 42825 | E6: ='Data Sheet'!D16 -> 43190 | F6: ='Data Sheet'!E16 -> 43555 | G6: ='Data Sheet'!F16 -> 43921 | H6: ='Data Sheet'!G16 -> 44286 | I6: ='Data Sheet'!H16 -> 44651 | J6: ='Data Sheet'!I16 -> 45016 | ... L6: ='Data Sheet'!K16 -> 45747
A8: # | B8: ="Common Size Income statement - " &'Data Sheet'!$B$1 -> Common Size Income statement - HINDUSTAN UNILEVER LTD
B10: Sales | C10: ='Data Sheet'!B17/'Data Sheet'!B$17 -> 1 | D10: ='Data Sheet'!C17/'Data Sheet'!C$17 -> 1 | E10: ='Data Sheet'!D17/'Data Sheet'!D$17 -> 1 | F10: ='Data Sheet'!E17/'Data Sheet'!E$17 -> 1 | G10: ='Data Sheet'!F17/'Data Sheet'!F$17 -> 1 | H10: ='Data Sheet'!G17/'Data Sheet'!G$17 -> 1 | I10: ='Data Sheet'!H17/'Data Sheet'!H$17 -> 1 | J10: ='Data Sheet'!I17/'Data Sheet'!I$17 -> 1 | ... L10: ='Data Sheet'!K17/'Data Sheet'!K$17 -> 1
B11: Raw Material Cost | C11: ='Data Sheet'!B18/'Data Sheet'!B$17 -> 0.40961909 | D11: ='Data Sheet'!C18/'Data Sheet'!C$17 -> 0.41028888 | E11: ='Data Sheet'!D18/'Data Sheet'!D$17 -> 0.400422 | F11: ='Data Sheet'!E18/'Data Sheet'!E$17 -> 0.4030781 | G11: ='Data Sheet'!F18/'Data Sheet'!F$17 -> 0.39456552 | H11: ='Data Sheet'!G18/'Data Sheet'!G$17 -> 0.42827677 | I11: ='Data Sheet'!H18/'Data Sheet'!H$17 -> 0.43608664 | J11: ='Data Sheet'!I18/'Data Sheet'!I$17 -> 0.46924728 | ... L11: ='Data Sheet'!K18/'Data Sheet'!K$17 -> 0.43319973
B12: Change in Inventory | C12: ='Data Sheet'!B19/'Data Sheet'!B$17 -> -0.002578761 | D12: ='Data Sheet'!C19/'Data Sheet'!C$17 -> -0.0043423195 | E12: ='Data Sheet'!D19/'Data Sheet'!D$17 -> 0.0020256014 | F12: ='Data Sheet'!E19/'Data Sheet'!E$17 -> -0.00030526584 | G12: ='Data Sheet'!F19/'Data Sheet'!F$17 -> 0.0027147274 | H12: ='Data Sheet'!G19/'Data Sheet'!G$17 -> 0.0086118908 | I12: ='Data Sheet'!H19/'Data Sheet'!H$17 -> 0.00041947908 | J12: ='Data Sheet'!I19/'Data Sheet'!I$17 -> 0.0012380324 | ... L12: ='Data Sheet'!K19/'Data Sheet'!K$17 -> 0.002423916
B13: Power and Fuel | C13: ='Data Sheet'!B20/'Data Sheet'!B$17 -> 0.0096004474 | D13: ='Data Sheet'!C20/'Data Sheet'!C$17 -> 0.008895724 | E13: ='Data Sheet'!D20/'Data Sheet'!D$17 -> 0.0082993389 | F13: ='Data Sheet'!E20/'Data Sheet'!E$17 -> 0.0078351564 | G13: ='Data Sheet'!F20/'Data Sheet'!F$17 -> 0.0075157731 | H13: ='Data Sheet'!G20/'Data Sheet'!G$17 -> 0.0072084715 | I13: ='Data Sheet'!H20/'Data Sheet'!H$17 -> 0.0060633795 | J13: ='Data Sheet'!I20/'Data Sheet'!I$17 -> 0.0063387257 | ... L13: ='Data Sheet'!K20/'Data Sheet'!K$17 -> 0.0067647851
B14: Other Mfr. Exp | C14: ='Data Sheet'!B21/'Data Sheet'!B$17 -> 0.092151867 | D14: ='Data Sheet'!C21/'Data Sheet'!C$17 -> 0.087057475 | E14: ='Data Sheet'!D21/'Data Sheet'!D$17 -> 0.08434379 | F14: ='Data Sheet'!E21/'Data Sheet'!E$17 -> 0.077359451 | G14: ='Data Sheet'!F21/'Data Sheet'!F$17 -> 0.073046276 | H14: ='Data Sheet'!G21/'Data Sheet'!G$17 -> 0.060984945 | I14: ='Data Sheet'!H21/'Data Sheet'!H$17 -> 0.063951493 | J14: ='Data Sheet'!I21/'Data Sheet'!I$17 -> 0.062578409 | ... L14: ='Data Sheet'!K21/'Data Sheet'!K$17 -> 0.060740483
B15: Employee Cost | C15: ='Data Sheet'!B22/'Data Sheet'!B$17 -> 0.052196607 | D15: ='Data Sheet'!C22/'Data Sheet'!C$17 -> 0.052560159 | E15: ='Data Sheet'!D22/'Data Sheet'!D$17 -> 0.052328035 | F15: ='Data Sheet'!E22/'Data Sheet'!E$17 -> 0.047697787 | G15: ='Data Sheet'!F22/'Data Sheet'!F$17 -> 0.045748184 | H15: ='Data Sheet'!G22/'Data Sheet'!G$17 -> 0.050140342 | I15: ='Data Sheet'!H22/'Data Sheet'!H$17 -> 0.048526103 | J15: ='Data Sheet'!I22/'Data Sheet'!I$17 -> 0.047111258 | ... L15: ='Data Sheet'!K22/'Data Sheet'!K$17 -> 0.048747643
B16: Selling and admin | C16: ='Data Sheet'!B23/'Data Sheet'!B$17 -> 0.20943889 | D16: ='Data Sheet'!C23/'Data Sheet'!C$17 -> 0.20170677 | E16: ='Data Sheet'!D23/'Data Sheet'!D$17 -> 0.20402307 | F16: ='Data Sheet'!E23/'Data Sheet'!E$17 -> 0.19832104 | G16: ='Data Sheet'!F23/'Data Sheet'!F$17 -> 0.1915391 | H16: ='Data Sheet'!G23/'Data Sheet'!G$17 -> 0.16811261 | I16: ='Data Sheet'!H23/'Data Sheet'!H$17 -> 0.15566487 | J16: ='Data Sheet'!I23/'Data Sheet'!I$17 -> 0.14501486 | ... L16: ='Data Sheet'!K23/'Data Sheet'!K$17 -> 0.16940479
B17: Other Expenses | C17: ='Data Sheet'!B24/'Data Sheet'!B$17 -> 0.040794134 | D17: ='Data Sheet'!C24/'Data Sheet'!C$17 -> 0.044327845 | E17: ='Data Sheet'!D24/'Data Sheet'!D$17 -> 0.041637361 | F17: ='Data Sheet'!E24/'Data Sheet'!E$17 -> 0.039506487 | G17: ='Data Sheet'!F24/'Data Sheet'!F$17 -> 0.042430184 | H17: ='Data Sheet'!G24/'Data Sheet'!G$17 -> 0.046674322 | I17: ='Data Sheet'!H24/'Data Sheet'!H$17 -> 0.044979598 | J17: ='Data Sheet'!I24/'Data Sheet'!I$17 -> 0.037421591 | ... L17: ='Data Sheet'!K24/'Data Sheet'!K$17 -> 0.048414949
B18: Other Income | C18: ='Data Sheet'!B25/'Data Sheet'!B$17 -> 0.015099733 | D18: ='Data Sheet'!C25/'Data Sheet'!C$17 -> 0.018273928 | E18: ='Data Sheet'!D25/'Data Sheet'!D$17 -> 0.0099310733 | F18: ='Data Sheet'!E25/'Data Sheet'!E$17 -> 0.0081912999 | G18: ='Data Sheet'!F25/'Data Sheet'!F$17 -> 0.010657819 | H18: ='Data Sheet'!G25/'Data Sheet'!G$17 -> 0.0036148677 | I18: ='Data Sheet'!H25/'Data Sheet'!H$17 -> 0.0041757236 | J18: ='Data Sheet'!I25/'Data Sheet'!I$17 -> 0.0073951799 | ... L18: ='Data Sheet'!K25/'Data Sheet'!K$17 -> 0.020943901
B19: Depreciation | C19: ='Data Sheet'!B26/'Data Sheet'!B$17 -> 0.010967501 | D19: ='Data Sheet'!C26/'Data Sheet'!C$17 -> 0.013026959 | E19: ='Data Sheet'!D26/'Data Sheet'!D$17 -> 0.014629343 | F19: ='Data Sheet'!E26/'Data Sheet'!E$17 -> 0.014372933 | G19: ='Data Sheet'!F26/'Data Sheet'!F$17 -> 0.025186638 | H19: ='Data Sheet'!G26/'Data Sheet'!G$17 -> 0.022837459 | I19: ='Data Sheet'!H26/'Data Sheet'!H$17 -> 0.020802349 | J19: ='Data Sheet'!I26/'Data Sheet'!I$17 -> 0.01876857 | ... L19: ='Data Sheet'!K26/'Data Sheet'!K$17 -> 0.021466707
B20: Interest | C20: ='Data Sheet'!B27/'Data Sheet'!B$17 -> 0.00052817995 | D20: ='Data Sheet'!C27/'Data Sheet'!C$17 -> 0.0010554249 | E20: ='Data Sheet'!D27/'Data Sheet'!D$17 -> 0.00073146715 | F20: ='Data Sheet'!E27/'Data Sheet'!E$17 -> 0.00083948105 | G20: ='Data Sheet'!F27/'Data Sheet'!F$17 -> 0.002966091 | H20: ='Data Sheet'!G27/'Data Sheet'!G$17 -> 0.0024878796 | I20: ='Data Sheet'!H27/'Data Sheet'!H$17 -> 0.0020211265 | J20: ='Data Sheet'!I27/'Data Sheet'!I$17 -> 0.0018818092 | ... L20: ='Data Sheet'!K27/'Data Sheet'!K$17 -> 0.0062578223
B21: Profit before tax | C21: ='Data Sheet'!B28/'Data Sheet'!B$17 -> 0.18722426 | D21: ='Data Sheet'!C28/'Data Sheet'!C$17 -> 0.19501236 | E21: ='Data Sheet'!D28/'Data Sheet'!D$17 -> 0.20554227 | F21: ='Data Sheet'!E28/'Data Sheet'!E$17 -> 0.2188756 | G21: ='Data Sheet'!F28/'Data Sheet'!F$17 -> 0.23037478 | H21: ='Data Sheet'!G28/'Data Sheet'!G$17 -> 0.22550396 | I21: ='Data Sheet'!H28/'Data Sheet'!H$17 -> 0.22649964 | J21: ='Data Sheet'!I28/'Data Sheet'!I$17 -> 0.22027072 | ... L21: ='Data Sheet'!K28/'Data Sheet'!K$17 -> 0.22837091
B22: Net profit | C22: ='Data Sheet'!B30/'Data Sheet'!B$17 -> 0.12896912 | D22: ='Data Sheet'!C30/'Data Sheet'!C$17 -> 0.13497377 | E22: ='Data Sheet'!D30/'Data Sheet'!D$17 -> 0.1466873 | F22: ='Data Sheet'!E30/'Data Sheet'!E$17 -> 0.15400661 | G22: ='Data Sheet'!F30/'Data Sheet'!F$17 -> 0.16962019 | H22: ='Data Sheet'!G30/'Data Sheet'!G$17 -> 0.1700051 | I22: ='Data Sheet'!H30/'Data Sheet'!H$17 -> 0.16929794 | J22: ='Data Sheet'!I30/'Data Sheet'!I$17 -> 0.16705183 | ... L22: ='Data Sheet'!K30/'Data Sheet'!K$17 -> 0.16870772
B23: Dividend Amount | C23: ='Data Sheet'!B31/'Data Sheet'!B$17 -> 0.10737588 | D23: ='Data Sheet'!C31/'Data Sheet'!C$17 -> 0.11072915 | E23: ='Data Sheet'!D31/'Data Sheet'!D$17 -> 0.12153608 | F23: ='Data Sheet'!E31/'Data Sheet'!E$17 -> 0.12088527 | G23: ='Data Sheet'!F31/'Data Sheet'!F$17 -> 0.13573637 | H23: ='Data Sheet'!G31/'Data Sheet'!G$17 -> 0.20237943 | I23: ='Data Sheet'!H31/'Data Sheet'!H$17 -> 0.15234718 | J23: ='Data Sheet'!I31/'Data Sheet'!I$17 -> 0.15128755 | ... L23: ='Data Sheet'!K31/'Data Sheet'!K$17 -> 0.19731943
A25: # | B25: ="Common Size Balance Sheet - " &'Data Sheet'!$B$1 -> Common Size Balance Sheet - HINDUSTAN UNILEVER LTD
B27: Total Liabilites | C27: ='Data Sheet'!B61/'Data Sheet'!B$61 -> 1 | D27: ='Data Sheet'!C61/'Data Sheet'!C$61 -> 1 | E27: ='Data Sheet'!D61/'Data Sheet'!D$61 -> 1 | F27: ='Data Sheet'!E61/'Data Sheet'!E$61 -> 1 | G27: ='Data Sheet'!F61/'Data Sheet'!F$61 -> 1 | H27: ='Data Sheet'!G61/'Data Sheet'!G$61 -> 1 | I27: ='Data Sheet'!H61/'Data Sheet'!H$61 -> 1 | J27: ='Data Sheet'!I61/'Data Sheet'!I$61 -> 1 | ... L27: ='Data Sheet'!K61/'Data Sheet'!K$61 -> 1
B29: Equity Share Capital | C29: ='Data Sheet'!B57/'Data Sheet'!B$61 -> 0.014601501 | D29: ='Data Sheet'!C57/'Data Sheet'!C$61 -> 0.013752706 | E29: ='Data Sheet'!D57/'Data Sheet'!D$61 -> 0.012092711 | F29: ='Data Sheet'!E57/'Data Sheet'!E$61 -> 0.011594825 | G29: ='Data Sheet'!F57/'Data Sheet'!F$61 -> 0.010718007 | H29: ='Data Sheet'!G57/'Data Sheet'!G$61 -> 0.0034186791 | I29: ='Data Sheet'!H57/'Data Sheet'!H$61 -> 0.0033330497 | J29: ='Data Sheet'!I57/'Data Sheet'!I$61 -> 0.0032157861 | ... L29: ='Data Sheet'!K57/'Data Sheet'!K$61 -> 0.0029425391
B30: Reserves | C30: ='Data Sheet'!B58/'Data Sheet'!B$61 -> 0.42973028 | D30: ='Data Sheet'!C58/'Data Sheet'!C$61 -> 0.41563734 | E30: ='Data Sheet'!D58/'Data Sheet'!D$61 -> 0.39553242 | F30: ='Data Sheet'!E58/'Data Sheet'!E$61 -> 0.41070374 | G30: ='Data Sheet'!F58/'Data Sheet'!F$61 -> 0.3976083 | H30: ='Data Sheet'!G58/'Data Sheet'!G$61 -> 0.6901222 | I30: ='Data Sheet'!H58/'Data Sheet'!H$61 -> 0.69250844 | J30: ='Data Sheet'!I58/'Data Sheet'!I$61 -> 0.68515402 | ... L30: ='Data Sheet'!K58/'Data Sheet'!K$61 -> 0.61564179
B31: Borrowings | C31: ='Data Sheet'!B59/'Data Sheet'!B$61 -> 0.011965119 | D31: ='Data Sheet'!C59/'Data Sheet'!C$61 -> 0.017636572 | E31: ='Data Sheet'!D59/'Data Sheet'!D$61 -> 0 | F31: ='Data Sheet'!E59/'Data Sheet'!E$61 -> 0.0053142949 | G31: ='Data Sheet'!F59/'Data Sheet'!F$61 -> 0 | H31: ='Data Sheet'!G59/'Data Sheet'!G$61 -> 0 | I31: ='Data Sheet'!H59/'Data Sheet'!H$61 -> 0.014793067 | J31: ='Data Sheet'!I59/'Data Sheet'!I$61 -> 0.016681035 | ... L31: ='Data Sheet'!K59/'Data Sheet'!K$61 -> 0.020635338
B32: Other Liabilities | C32: ='Data Sheet'!B60/'Data Sheet'!B$61 -> 0.5437031 | D32: ='Data Sheet'!C60/'Data Sheet'!C$61 -> 0.55297339 | E32: ='Data Sheet'!D60/'Data Sheet'!D$61 -> 0.59237487 | F32: ='Data Sheet'!E60/'Data Sheet'!E$61 -> 0.57238714 | G32: ='Data Sheet'!F60/'Data Sheet'!F$61 -> 0.5916737 | H32: ='Data Sheet'!G60/'Data Sheet'!G$61 -> 0.30645912 | I32: ='Data Sheet'!H60/'Data Sheet'!H$61 -> 0.28936544 | J32: ='Data Sheet'!I60/'Data Sheet'!I$61 -> 0.29494916 | ... L32: ='Data Sheet'!K60/'Data Sheet'!K$61 -> 0.36078034
B34: Total Assets | C34: =C44+C40 -> 1 | D34: =D44+D40 -> 1 | E34: =E44+E40 -> 1 | F34: =F44+F40 -> 1 | G34: =G44+G40 -> 1 | H34: =H44+H40 -> 1 | I34: =I44+I40 -> 1 | J34: =J44+J40 -> 1 | ... L34: =L44+L40 -> 1
B36: Net Block | C36: ='Data Sheet'!B62/'Data Sheet'!B$66 -> 0.2202393 | D36: ='Data Sheet'!C62/'Data Sheet'!C$66 -> 0.28135744 | E36: ='Data Sheet'!D62/'Data Sheet'!D$66 -> 0.25349905 | F36: ='Data Sheet'!E62/'Data Sheet'!E$66 -> 0.25310001 | G36: ='Data Sheet'!F62/'Data Sheet'!F$66 -> 0.27187019 | H36: ='Data Sheet'!G62/'Data Sheet'!G$66 -> 0.74837067 | I36: ='Data Sheet'!H62/'Data Sheet'!H$66 -> 0.73005134 | J36: ='Data Sheet'!I62/'Data Sheet'!I$66 -> 0.72085608 | ... L36: ='Data Sheet'!K62/'Data Sheet'!K$66 -> 0.6803526
B37: Capital Work in Progress | C37: ='Data Sheet'!B63/'Data Sheet'!B$66 -> 0.027580612 | D37: ='Data Sheet'!C63/'Data Sheet'!C$66 -> 0.014580415 | E37: ='Data Sheet'!D63/'Data Sheet'!D$66 -> 0.02580898 | F37: ='Data Sheet'!E63/'Data Sheet'!E$66 -> 0.021793977 | G37: ='Data Sheet'!F63/'Data Sheet'!F$66 -> 0.029623381 | H37: ='Data Sheet'!G63/'Data Sheet'!G$66 -> 0.01083794 | I37: ='Data Sheet'!H63/'Data Sheet'!H$66 -> 0.018622529 | J37: ='Data Sheet'!I63/'Data Sheet'!I$66 -> 0.01549051 | ... L37: ='Data Sheet'!K63/'Data Sheet'!K$66 -> 0.012634136
B38: Investments | C38: ='Data Sheet'!B64/'Data Sheet'!B$66 -> 0.17521801 | D38: ='Data Sheet'!C64/'Data Sheet'!C$66 -> 0.24156373 | E38: ='Data Sheet'!D64/'Data Sheet'!D$66 -> 0.16084425 | F38: ='Data Sheet'!E64/'Data Sheet'!E$66 -> 0.14579419 | G38: ='Data Sheet'!F64/'Data Sheet'!F$66 -> 0.062273607 | H38: ='Data Sheet'!G64/'Data Sheet'!G$66 -> 0.039409369 | I38: ='Data Sheet'!H64/'Data Sheet'!H$66 -> 0.049939012 | J38: ='Data Sheet'!I64/'Data Sheet'!I$66 -> 0.039437853 | ... L38: ='Data Sheet'!K64/'Data Sheet'!K$66 -> 0.047706698
B39: Other Assets | C39: =('Data Sheet'!B65-SUM('Data Sheet'!B67:B69))/'Data Sheet'!B$66 -> 0.10383289 | D39: =('Data Sheet'!C65-SUM('Data Sheet'!C67:C69))/'Data Sheet'!C$66 -> 0.11524258 | E39: =('Data Sheet'!D65-SUM('Data Sheet'!D67:D69))/'Data Sheet'!D$66 -> 0.15071101 | F39: =('Data Sheet'!E65-SUM('Data Sheet'!E67:E69))/'Data Sheet'!E$66 -> 0.14198293 | G39: =('Data Sheet'!F65-SUM('Data Sheet'!F67:F69))/'Data Sheet'!F$66 -> 0.18821019 | H39: =('Data Sheet'!G65-SUM('Data Sheet'!G67:G69))/'Data Sheet'!G$66 -> 0.058699447 | I39: =('Data Sheet'!H65-SUM('Data Sheet'!H67:H69))/'Data Sheet'!H$66 -> 0.057030607 | J39: =('Data Sheet'!I65-SUM('Data Sheet'!I67:I69))/'Data Sheet'!I$66 -> 0.059895726 | ... L39: =('Data Sheet'!K65-SUM('Data Sheet'!K67:K69))/'Data Sheet'!K$66 -> 0.061618021
B40: Total Non Current Assets | C40: =SUM(C36:C39) -> 0.52687082 | D40: =SUM(D36:D39) -> 0.65274417 | E40: =SUM(E36:E39) -> 0.59086329 | F40: =SUM(F36:F39) -> 0.5626711 | G40: =SUM(G36:G39) -> 0.55197737 | H40: =SUM(H36:H39) -> 0.85731743 | I40: =SUM(I36:I39) -> 0.85564349 | J40: =SUM(J36:J39) -> 0.83568017 | ... L40: =SUM(L36:L39) -> 0.80231146
B41: Receivables | C41: ='Data Sheet'!B67/'Data Sheet'!B$66 -> 0.085445819 | D41: ='Data Sheet'!C67/'Data Sheet'!C$66 -> 0.06908188 | E41: ='Data Sheet'!D67/'Data Sheet'!D$66 -> 0.073340052 | F41: ='Data Sheet'!E67/'Data Sheet'!E$66 -> 0.09748242 | G41: ='Data Sheet'!F67/'Data Sheet'!F$66 -> 0.057013844 | H41: ='Data Sheet'!G67/'Data Sheet'!G$66 -> 0.025574629 | I41: ='Data Sheet'!H67/'Data Sheet'!H$66 -> 0.031713613 | J41: ='Data Sheet'!I67/'Data Sheet'!I$66 -> 0.04213364 | ... L41: ='Data Sheet'!K67/'Data Sheet'!K$66 -> 0.047819391
B42: Inventory | C42: ='Data Sheet'!B68/'Data Sheet'!B$66 -> 0.18427635 | D42: ='Data Sheet'!C68/'Data Sheet'!C$66 -> 0.1617853 | E42: ='Data Sheet'!D68/'Data Sheet'!D$66 -> 0.14068973 | F42: ='Data Sheet'!E68/'Data Sheet'!E$66 -> 0.13817167 | G42: ='Data Sheet'!F68/'Data Sheet'!F$66 -> 0.13729966 | H42: ='Data Sheet'!G68/'Data Sheet'!G$66 -> 0.052065755 | I42: ='Data Sheet'!H68/'Data Sheet'!H$66 -> 0.058094347 | J42: ='Data Sheet'!I68/'Data Sheet'!I$66 -> 0.058171518 | ... L42: ='Data Sheet'!K68/'Data Sheet'!K$66 -> 0.055282171
B43: Cash & Bank | C43: ='Data Sheet'!B69/'Data Sheet'!B$66 -> 0.20340702 | D43: ='Data Sheet'!C69/'Data Sheet'!C$66 -> 0.11638864 | E43: ='Data Sheet'!D69/'Data Sheet'!D$66 -> 0.19510693 | F43: ='Data Sheet'!E69/'Data Sheet'!E$66 -> 0.20167481 | G43: ='Data Sheet'!F69/'Data Sheet'!F$66 -> 0.25370913 | H43: ='Data Sheet'!G69/'Data Sheet'!G$66 -> 0.065042188 | I43: ='Data Sheet'!H69/'Data Sheet'!H$66 -> 0.054548549 | J43: ='Data Sheet'!I69/'Data Sheet'!I$66 -> 0.064014669 | ... L43: ='Data Sheet'!K69/'Data Sheet'!K$66 -> 0.09458698
B44: Total Current Assets | C44: =SUM('Data Sheet'!B67:B69)/'Data Sheet'!B66 -> 0.47312918 | D44: =SUM('Data Sheet'!C67:C69)/'Data Sheet'!C66 -> 0.34725583 | E44: =SUM('Data Sheet'!D67:D69)/'Data Sheet'!D66 -> 0.40913671 | F44: =SUM('Data Sheet'!E67:E69)/'Data Sheet'!E66 -> 0.4373289 | G44: =SUM('Data Sheet'!F67:F69)/'Data Sheet'!F66 -> 0.44802263 | H44: =SUM('Data Sheet'!G67:G69)/'Data Sheet'!G66 -> 0.14268257 | I44: =SUM('Data Sheet'!H67:H69)/'Data Sheet'!H66 -> 0.14435651 | J44: =SUM('Data Sheet'!I67:I69)/'Data Sheet'!I66 -> 0.16431983 | ... L44: =SUM('Data Sheet'!K67:K69)/'Data Sheet'!K66 -> 0.19768854

Sheet Ratio Analysis
B1: HINDUSTAN UNILEVER
B5: ="Ratio Analysis - " &'Data Sheet'!B1 -> Ratio Analysis - HINDUSTAN UNILEVER LTD
B6: Years | C6: ='Data Sheet'!B16 -> 42460 | D6: ='Data Sheet'!C16 -> 42825 | E6: ='Data Sheet'!D16 -> 43190 | F6: ='Data Sheet'!E16 -> 43555 | G6: ='Data Sheet'!F16 -> 43921 | H6: ='Data Sheet'!G16 -> 44286 | I6: ='Data Sheet'!H16 -> 44651 | J6: ='Data Sheet'!I16 -> 45016 | ... L6: ='Data Sheet'!K16 -> 45747 | M6: Trend | N6: MEAN | O6: MEDIAN
B8: Sales Growth | D8: =IFERROR(Historicals!D11,0) -> 0.030323743 | E8: =IFERROR(Historicals!E11,0) -> 0.071859357 | F8: =IFERROR(Historicals!F11,0) -> 0.10592207 | G8: =IFERROR(Historicals!G11,0) -> 0.012032562 | H8: =IFERROR(Historicals!H11,0) -> 0.18211296 | I8: =IFERROR(Historicals!I11,0) -> 0.11520796 | J8: =IFERROR(Historicals!J11,0) -> 0.15509286 | K8: =IFERROR(Historicals!K11,0) -> 0.021723341 | L8: =IFERROR(Historicals!L11,0) -> 0.019791263 | N8: =IFERROR(AVERAGE(D8:L8),0) -> 0.07934068 | O8: =IFERROR(MEDIAN(D8:L8),0) -> 0.071859357
B9: EBITDA Growth | D9: =IFERROR(Historicals!D22/Historicals!C22-1,0) -> 0.07072758 | E9: =IFERROR(Historicals!E22/Historicals!D22-1,0) -> 0.18505057 | F9: =IFERROR(Historicals!F22/Historicals!E22-1,0) -> 0.18415789 | G9: =IFERROR(Historicals!G22/Historicals!F22-1,0) -> 0.11047297 | H9: =IFERROR(Historicals!H22/Historicals!G22-1,0) -> 0.17898793 | I9: =IFERROR(Historicals!I22/Historicals!H22-1,0) -> 0.10588336 | J9: =IFERROR(Historicals!J22/Historicals!I22-1,0) -> 0.10033445 | K9: =IFERROR(Historicals!K22/Historicals!J22-1,0) -> 0.036191419 | L9: =IFERROR(Historicals!L22/Historicals!K22-1,0) -> 0.012552016 | N9: =IFERROR(AVERAGE(D9:L9),0) -> 0.10937313 | O9: =IFERROR(MEDIAN(D9:L9),0) -> 0.10588336
B10: EBIT Growth | D10: =IFERROR((Historicals!D22-Historicals!D28)/(Historicals!C22-Historicals!C28)-1,0) -> 0.061004139 | E10: =IFERROR((Historicals!E22-Historicals!E28)/(Historicals!D22-Historicals!D28)-1,0) -> 0.18368385 | F10: =IFERROR((Historicals!F22-Historicals!F28)/(Historicals!E22-Historicals!E28)-1,0) -> 0.19143144 | G10: =IFERROR((Historicals!G22-Historicals!G28)/(Historicals!F22-Historicals!F28)-1,0) -> 0.065423933 | H10: =IFERROR((Historicals!H22-Historicals!H28)/(Historicals!G22-Historicals!G28)-1,0) -> 0.19110509 | I10: =IFERROR((Historicals!I22-Historicals!I28)/(Historicals!H22-Historicals!H28)-1,0) -> 0.11504928 | J10: =IFERROR((Historicals!J22-Historicals!J28)/(Historicals!I22-Historicals!I28)-1,0) -> 0.10572837 | K10: =IFERROR((Historicals!K22-Historicals!K28)/(Historicals!J22-Historicals!J28)-1,0) -> 0.033282091 | L10: =IFERROR((Historicals!L22-Historicals!L28)/(Historicals!K22-Historicals!K28)-1,0) -> 0.0033474671 | N10: =IFERROR(AVERAGE(D10:L10),0) -> 0.10556174 | O10: =IFERROR(MEDIAN(D10:L10),0) -> 0.10572837
B11: EBT Growth | D11: =IFERROR(Historicals!D31/Historicals!C31-1,0) -> 0.057942238 | E11: =IFERROR(Historicals!E31/Historicals!D31-1,0) -> 0.18631633 | F11: =IFERROR(Historicals!F31/Historicals!E31-1,0) -> 0.19114051 | G11: =IFERROR(Historicals!G31/Historicals!F31-1,0) -> 0.055421396 | H11: =IFERROR(Historicals!H31/Historicals!G31-1,0) -> 0.19379934 | I11: =IFERROR(Historicals!I31/Historicals!H31-1,0) -> 0.11739339 | J11: =IFERROR(Historicals!J31/Historicals!I31-1,0) -> 0.10600343 | K11: =IFERROR(Historicals!K31/Historicals!J31-1,0) -> 0.016516749 | L11: =IFERROR(Historicals!L31/Historicals!K31-1,0) -> -0.0012205355 | N11: =IFERROR(AVERAGE(D11:L11),0) -> 0.10259032 | O11: =IFERROR(MEDIAN(D11:L11),0) -> 0.10600343
B12: PAT Growth | D12: =IFERROR(Historicals!D37/Historicals!C37-1,0) -> 0.059754434 | E12: =IFERROR(Historicals!E37/Historicals!D37-1,0) -> 0.25489186 | F12: =IFERROR(Historicals!F37/Historicals!E37-1,0) -> 0.17726713 | G12: =IFERROR(Historicals!G37/Historicals!F37-1,0) -> 0.10352039 | H12: =IFERROR(Historicals!H37/Historicals!G37-1,0) -> 0.23641819 | I12: =IFERROR(Historicals!I37/Historicals!H37-1,0) -> 0.10780432 | J12: =IFERROR(Historicals!J37/Historicals!I37-1,0) -> 0.11783697 | K12: =IFERROR(Historicals!K37/Historicals!J37-1,0) -> -0.023723569 | L12: =IFERROR(Historicals!L37/Historicals!K37-1,0) -> -0.012255679 | N12: =IFERROR(AVERAGE(D12:L12),0) -> 0.11350156 | O12: =IFERROR(MEDIAN(D12:L12),0) -> 0.10780432
B13: Dividend Growth | D13: =IFERROR(Historicals!D45/Historicals!C45-1,0) -> 0.062303632 | E13: =IFERROR(Historicals!E45/Historicals!D45-1,0) -> 0.17636188 | F13: =IFERROR(Historicals!F45/Historicals!E45-1,0) -> 0.099898369 | G13: =IFERROR(Historicals!G45/Historicals!F45-1,0) -> 0.13631114 | H13: =IFERROR(Historicals!H45/Historicals!G45-1,0) -> 0.6238764 | I13: =IFERROR(Historicals!I45/Historicals!H45-1,0) -> -0.16049383 | J13: =IFERROR(Historicals!J45/Historicals!I45-1,0) -> 0.14705882 | K13: =IFERROR(Historicals!K45/Historicals!J45-1,0) -> 0.076923077 | L13: =IFERROR(Historicals!L45/Historicals!K45-1,0) -> 0.26190476 | N13: =IFERROR(AVERAGE(D13:L13),0) -> 0.15823825 | O13: =IFERROR(MEDIAN(D13:L13),0) -> 0.13631114
B15: Gross Margin | C15: =IFERROR(Historicals!C17,0) -> 0.43385323 | D15: =IFERROR(Historicals!D17,0) -> 0.43685544 | E15: =IFERROR(Historicals!E17,0) -> 0.45663244 | F15: =IFERROR(Historicals!F17,0) -> 0.46372424 | G15: =IFERROR(Historicals!G17,0) -> 0.48183898 | H15: =IFERROR(Historicals!H17,0) -> 0.46200136 | I15: =IFERROR(Historicals!I17,0) -> 0.44579186 | J15: =IFERROR(Historicals!J17,0) -> 0.41596236 | ... L15: =IFERROR(Historicals!L17,0) -> 0.45297128 | N15: =IFERROR(AVERAGE(C15:L15),0) -> 0.45059612 | O15: =IFERROR(MEDIAN(C15:L15),0) -> 0.45465063
B16: EBITDA Margin | C16: =IFERROR(Historicals!C23,0) -> 0.18362021 | D16: =IFERROR(Historicals!D23,0) -> 0.19082082 | E16: =IFERROR(Historicals!E23,0) -> 0.21097201 | F16: =IFERROR(Historicals!F23,0) -> 0.22589672 | G16: =IFERROR(Historicals!G23,0) -> 0.24786969 | H16: =IFERROR(Historicals!H23,0) -> 0.24721443 | I16: =IFERROR(Historicals!I23,0) -> 0.24514739 | J16: =IFERROR(Historicals!J23,0) -> 0.23352592 | ... L16: =IFERROR(Historicals!L23,0) -> 0.23515153 | N16: =IFERROR(AVERAGE(C16:L16),0) -> 0.22570515 | O16: =IFERROR(MEDIAN(C16:L16),0) -> 0.23433873
B17: EBIT Margin | C17: =IFERROR((Historicals!C22-Historicals!C28)/Historicals!C10,0) -> 0.17265271 | D17: =IFERROR((Historicals!D22-Historicals!D28)/Historicals!D10,0) -> 0.17779386 | E17: =IFERROR((Historicals!E22-Historicals!E28)/Historicals!E10,0) -> 0.19634266 | F17: =IFERROR((Historicals!F22-Historicals!F28)/Historicals!F10,0) -> 0.21152379 | G17: =IFERROR((Historicals!G22-Historicals!G28)/Historicals!G10,0) -> 0.22268306 | H17: =IFERROR((Historicals!H22-Historicals!H28)/Historicals!H10,0) -> 0.22437697 | I17: =IFERROR((Historicals!I22-Historicals!I28)/Historicals!I10,0) -> 0.22434504 | J17: =IFERROR((Historicals!J22-Historicals!J28)/Historicals!J10,0) -> 0.21475735 | ... L17: =IFERROR((Historicals!L22-Historicals!L28)/Historicals!L10,0) -> 0.21368483 | N17: =IFERROR(AVERAGE(C17:L17),0) -> 0.20753471 | O17: =IFERROR(MEDIAN(C17:L17),0) -> 0.21422109
B18: PBT Margin | C18: =IFERROR(Historicals!C32,) -> 0.17212453 | D18: =IFERROR(Historicals!D32,) -> 0.17673844 | E18: =IFERROR(Historicals!E32,) -> 0.1956112 | F18: =IFERROR(Historicals!F32,) -> 0.2106843 | G18: =IFERROR(Historicals!G32,) -> 0.21971696 | H18: =IFERROR(Historicals!H32,) -> 0.22188909 | I18: =IFERROR(Historicals!I32,) -> 0.22232391 | J18: =IFERROR(Historicals!J32,) -> 0.21287554 | ... L18: =IFERROR(Historicals!L32,) -> 0.20742701 | N18: =IFERROR(AVERAGE(C18:L18),0) -> 0.20511817 | O18: =IFERROR(MEDIAN(C18:L18),0) -> 0.21123753
B19: Net Profit Margin | C19: =IFERROR(Historicals!C38,0) -> 0.11386938 | D19: =IFERROR(Historicals!D38,0) -> 0.11712201 | E19: =IFERROR(Historicals!E38,0) -> 0.13712196 | F19: =IFERROR(Historicals!F38,0) -> 0.14596795 | G19: =IFERROR(Historicals!G38,0) -> 0.15916346 | H19: =IFERROR(Historicals!H38,0) -> 0.16647529 | I19: =IFERROR(Historicals!I38,0) -> 0.16537009 | J19: =IFERROR(Historicals!J38,0) -> 0.16003632 | ... L19: =IFERROR(Historicals!L38,0) -> 0.14811236 | N19: =IFERROR(AVERAGE(C19:L19),0) -> 0.14661566 | O19: =IFERROR(MEDIAN(C19:L19),0) -> 0.15051508
B21: SalesExpense%Sales | C21: =IFERROR(Historicals!C20,0) -> 0.25023302 | D21: =IFERROR(Historicals!D20,0) -> 0.24603462 | E21: =IFERROR(Historicals!E20,0) -> 0.24566043 | F21: =IFERROR(Historicals!F20,0) -> 0.23782752 | G21: =IFERROR(Historicals!G20,0) -> 0.23396928 | H21: =IFERROR(Historicals!H20,0) -> 0.21478694 | I21: =IFERROR(Historicals!I20,0) -> 0.20064447 | J21: =IFERROR(Historicals!J20,0) -> 0.18243645 | ... L21: =IFERROR(Historicals!L20,0) -> 0.21781974 | N21: =IFERROR(AVERAGE(C21:L21),0) -> 0.22489097 | O21: =IFERROR(MEDIAN(C21:L21),0) -> 0.22673325
B22: Depriciation%Sales | C22: =IFERROR(Historicals!C29,0) -> 0.010967501 | D22: =IFERROR(Historicals!D29,0) -> 0.013026959 | E22: =IFERROR(Historicals!E29,0) -> 0.014629343 | F22: =IFERROR(Historicals!F29,0) -> 0.014372933 | G22: =IFERROR(Historicals!G29,0) -> 0.025186638 | H22: =IFERROR(Historicals!H29,0) -> 0.022837459 | I22: =IFERROR(Historicals!I29,0) -> 0.020802349 | J22: =IFERROR(Historicals!J29,0) -> 0.01876857 | ... L22: =IFERROR(Historicals!L29,0) -> 0.021466707 | N22: =IFERROR(AVERAGE(C22:L22),0) -> 0.018170432 | O22: =IFERROR(MEDIAN(C22:L22),0) -> 0.019207214
B23: OperatingIncome%Sales | C23: =C16 -> 0.18362021 | D23: =D16 -> 0.19082082 | E23: =E16 -> 0.21097201 | F23: =F16 -> 0.22589672 | G23: =G16 -> 0.24786969 | H23: =H16 -> 0.24721443 | I23: =I16 -> 0.24514739 | J23: =J16 -> 0.23352592 | ... L23: =L16 -> 0.23515153 | N23: =IFERROR(AVERAGE(C23:L23),0) -> 0.22570515 | O23: =IFERROR(MEDIAN(C23:L23),0) -> 0.23433873
B25: ReturnOnCapitalEmployed | C25: =IFERROR((Historicals!C22-Historicals!C28)/(SUM(Historicals!C53:C55)),0) -> 0.82325926 | D25: =IFERROR((Historicals!D22-Historicals!D28)/(SUM(Historicals!D53:D55)),0) -> 0.83976642 | E25: =IFERROR((Historicals!E22-Historicals!E28)/(SUM(Historicals!E53:E55)),0) -> 0.95852218 | F25: =IFERROR((Historicals!F22-Historicals!F28)/(SUM(Historicals!F53:F55)),0) -> 1.0438112 | G25: =IFERROR((Historicals!G22-Historicals!G28)/(SUM(Historicals!G53:G55)),0) -> 1.0765585 | H25: =IFERROR((Historicals!H22-Historicals!H28)/(SUM(Historicals!H53:H55)),0) -> 0.22133658 | I25: =IFERROR((Historicals!I22-Historicals!I28)/(SUM(Historicals!I53:I55)),0) -> 0.23483155 | J25: =IFERROR((Historicals!J22-Historicals!J28)/(SUM(Historicals!J53:J55)),0) -> 0.25250859 | ... L25: =IFERROR((Historicals!L22-Historicals!L28)/(SUM(Historicals!L53:L55)),0) -> 0.26421156 | N25: =IFERROR(AVERAGE(C25:L25),0) -> 0.59698815 | O25: =IFERROR(MEDIAN(C25:L25),0) -> 0.54373541
B26: Retained Earning % | C26: =IFERROR(Historicals!C48,0) -> 0.057025921 | D26: =IFERROR(Historicals!D48,0) -> 0.054582904 | E26: =IFERROR(Historicals!E48,0) -> 0.11366434 | F26: =IFERROR(Historicals!F48,0) -> 0.17183688 | G26: =IFERROR(Historicals!G48,0) -> 0.14718888 | H26: =IFERROR(Historicals!H48,0) -> -0.2156725 | I26: =IFERROR(Historicals!I48,0) -> 0.078750144 | J26: =IFERROR(Historicals!J48,0) -> 0.054667354 | ... L26: =IFERROR(Historicals!L48,0) -> -0.33222805 | N26: =IFERROR(AVERAGE(C26:L26),0) -> 0.0087026655 | O26: =IFERROR(MEDIAN(C26:L26),0) -> 0.055846638
B27: Return On equity | C27: =IFERROR(Historicals!C37/(SUM(Historicals!C53:C54)),0) -> 0.55758406 | D27: =IFERROR(Historicals!D37/(SUM(Historicals!D53:D54)),0) -> 0.57591934 | E27: =IFERROR(Historicals!E37/(SUM(Historicals!E53:E54)),0) -> 0.66941354 | F27: =IFERROR(Historicals!F37/(SUM(Historicals!F53:F54)),0) -> 0.72937587 | G27: =IFERROR(Historicals!G37/(SUM(Historicals!G53:G54)),0) -> 0.76947381 | H27: =IFERROR(Historicals!H37/(SUM(Historicals!H53:H54)),0) -> 0.16421949 | I27: =IFERROR(Historicals!I37/(SUM(Historicals!I53:I54)),0) -> 0.17677993 | J27: =IFERROR(Historicals!J37/(SUM(Historicals!J53:J54)),0) -> 0.19272821 | ... L27: =IFERROR(Historicals!L37/(SUM(Historicals!L53:L54)),0) -> 0.18924335 | N27: =IFERROR(AVERAGE(C27:L27),0) -> 0.42095359 | O27: =IFERROR(MEDIAN(C27:L27),0) -> 0.37515613
B28: Self Sustained Growth Rate | C28: =IFERROR(C27*C26,0) -> 0.031796744 | D28: =IFERROR(D27*D26,0) -> 0.03143535 | E28: =IFERROR(E27*E26,0) -> 0.076088449 | F28: =IFERROR(F27*F26,0) -> 0.12533367 | G28: =IFERROR(G27*G26,0) -> 0.11325799 | H28: =IFERROR(H27*H26,0) -> -0.035417628 | I28: =IFERROR(I27*I26,0) -> 0.013921445 | J28: =IFERROR(J27*J26,0) -> 0.010535941 | ... L28: =IFERROR(L27*L26,0) -> -0.062871949 | N28: =IFERROR(AVERAGE(C28:L28),0) -> 0.029617264 | O28: =IFERROR(MEDIAN(C28:L28),0) -> 0.022678397
B29: Interest Coverage Ratio | C29: =IFERROR((Historicals!C22-Historicals!C28)/Historicals!C25,0) -> 326.88235 | D29: =IFERROR((Historicals!D22-Historicals!D28)/Historicals!D25,0) -> 168.45714 | E29: =IFERROR((Historicals!E22-Historicals!E28)/Historicals!E25,0) -> 268.42308 | F29: =IFERROR((Historicals!F22-Historicals!F28)/Historicals!F25,0) -> 251.9697 | G29: =IFERROR((Historicals!G22-Historicals!G28)/Historicals!G25,0) -> 75.076271 | H29: =IFERROR((Historicals!H22-Historicals!H28)/Historicals!H25,0) -> 90.188034 | I29: =IFERROR((Historicals!I22-Historicals!I28)/Historicals!I25,0) -> 111 | J29: =IFERROR((Historicals!J22-Historicals!J28)/Historicals!J25,0) -> 114.12281 | ... L29: =IFERROR((Historicals!L22-Historicals!L28)/Historicals!L25,0) -> 34.146835 | N29: =IFERROR(AVERAGE(C29:L29),0) -> 148.05147 | O29: =IFERROR(MEDIAN(C29:L29),0) -> 112.5614
B31: Debtor Turnover Ratio | C31: =IFERROR(Historicals!C10/Historicals!C65,0) -> 25.463608 | D31: =IFERROR(Historicals!D10/Historicals!D65,0) -> 30.564055 | E31: =IFERROR(Historicals!E10/Historicals!E65,0) -> 27.133588 | F31: =IFERROR(Historicals!F10/Historicals!F65,0) -> 21.646476 | G31: =IFERROR(Historicals!G10/Historicals!G65,0) -> 34.624021 | H31: =IFERROR(Historicals!H10/Historicals!H65,0) -> 26.750853 | I31: =IFERROR(Historicals!I10/Historicals!I65,0) -> 23.455277 | J31: =IFERROR(Historicals!J10/Historicals!J65,0) -> 19.675219 | ... L31: =IFERROR(Historicals!L10/Historicals!L65,0) -> 16.528149 | N31: =IFERROR(AVERAGE(C31:L31),0) -> 24.64939 | O31: =IFERROR(MEDIAN(C31:L31),0) -> 24.459442
B32: Creditor Turnover Ratio | C32: =IFERROR(Historicals!C13/Historicals!C56,0) -> 2.2655725 | D32: =IFERROR(Historicals!D13/Historicals!D56,0) -> 2.1502591 | E32: =IFERROR(Historicals!E13/Historicals!E56,0) -> 1.8253473 | F32: =IFERROR(Historicals!F13/Historicals!F56,0) -> 1.9770234 | G32: =IFERROR(Historicals!G13/Historicals!G56,0) -> 1.7287823 | H32: =IFERROR(Historicals!H13/Historicals!H56,0) -> 1.2010348 | I32: =IFERROR(Historicals!I13/Historicals!I56,0) -> 1.4246642 | J32: =IFERROR(Historicals!J13/Historicals!J56,0) -> 1.6415051 | ... L32: =IFERROR(Historicals!L13/Historicals!L56,0) -> 1.1983827 | N32: =IFERROR(AVERAGE(C32:L32),0) -> 1.6717531 | O32: =IFERROR(MEDIAN(C32:L32),0) -> 1.6851437
B33: Inventory Turnover Ratio | C33: =IFERROR(Historicals!C13/Historicals!C66,0) -> 6.6845194 | D33: =IFERROR(Historicals!D13/Historicals!D66,0) -> 7.3494687 | E33: =IFERROR(Historicals!E13/Historicals!E66,0) -> 7.6856347 | F33: =IFERROR(Historicals!F13/Historicals!F66,0) -> 8.1899767 | G33: =IFERROR(Historicals!G13/Historicals!G66,0) -> 7.4499458 | H33: =IFERROR(Historicals!H13/Historicals!H66,0) -> 7.0692931 | I33: =IFERROR(Historicals!I13/Historicals!I66,0) -> 7.0961914 | J33: =IFERROR(Historicals!J13/Historicals!J66,0) -> 8.3229828 | ... L33: =IFERROR(Historicals!L13/Historicals!L66,0) -> 7.8208381 | N33: =IFERROR(AVERAGE(C33:L33),0) -> 7.6035584 | O33: =IFERROR(MEDIAN(C33:L33),0) -> 7.5677902
B34: Fixed Asset Turnover Ratio | C34: =IFERROR(Historicals!C10/Historicals!C59,0) -> 9.8790669 | D34: =IFERROR(Historicals!D10/Historicals!D59,0) -> 7.5044128 | E34: =IFERROR(Historicals!E10/Historicals!E59,0) -> 7.8500442 | F34: =IFERROR(Historicals!F10/Historicals!F59,0) -> 8.3372216 | G34: =IFERROR(Historicals!G10/Historicals!G59,0) -> 7.2609965 | H34: =IFERROR(Historicals!H10/Historicals!H59,0) -> 0.91417686 | I34: =IFERROR(Historicals!I10/Historicals!I59,0) -> 1.0189031 | J34: =IFERROR(Historicals!J10/Historicals!J59,0) -> 1.1500057 | ... L34: =IFERROR(Historicals!L10/Historicals!L59,0) -> 1.1617006 | N34: =IFERROR(AVERAGE(C34:L34),0) -> 4.622821 | O34: =IFERROR(MEDIAN(C34:L34),0) -> 4.2113485
B35: Capital Turnover Ratio | C35: =IFERROR(Historicals!C10/SUM(Historicals!C53:C54),0) -> 4.8966986 | D35: =IFERROR(Historicals!D10/SUM(Historicals!D53:D54),0) -> 4.9172598 | E35: =IFERROR(Historicals!E10/SUM(Historicals!E53:E54),0) -> 4.8818844 | F35: =IFERROR(Historicals!F10/SUM(Historicals!F53:F54),0) -> 4.9968222 | G35: =IFERROR(Historicals!G10/SUM(Historicals!G53:G54),0) -> 4.8344878 | H35: =IFERROR(Historicals!H10/SUM(Historicals!H53:H54),0) -> 0.98644964 | I35: =IFERROR(Historicals!I10/SUM(Historicals!I53:I54),0) -> 1.0689957 | J35: =IFERROR(Historicals!J10/SUM(Historicals!J53:J54),0) -> 1.204278 | ... L35: =IFERROR(Historicals!L10/SUM(Historicals!L53:L54),0) -> 1.2777013 | N35: =IFERROR(AVERAGE(C35:L35),0) -> 3.0273059 | O35: =IFERROR(MEDIAN(C35:L35),0) -> 3.0560945
B37: Debtor Days | C37: =IFERROR(365/C31,0) -> 14.334183 | D37: =IFERROR(365/D31,0) -> 11.942133 | E37: =IFERROR(365/E31,0) -> 13.451962 | F37: =IFERROR(365/F31,0) -> 16.861867 | G37: =IFERROR(365/G31,0) -> 10.541814 | H37: =IFERROR(365/H31,0) -> 13.644425 | I37: =IFERROR(365/I31,0) -> 15.56153 | J37: =IFERROR(365/J31,0) -> 18.551255 | ... L37: =IFERROR(365/L31,0) -> 22.083538 | N37: =IFERROR(AVERAGE(C37:L37),0) -> 15.464598 | O37: =IFERROR(MEDIAN(C37:L37),0) -> 14.947856
B38: Payable Days | C38: =IFERROR(365/C32,0) -> 161.10718 | D38: =IFERROR(365/D32,0) -> 169.74699 | E38: =IFERROR(365/E32,0) -> 199.96194 | F38: =IFERROR(365/F32,0) -> 184.62099 | G38: =IFERROR(365/G32,0) -> 211.13127 | H38: =IFERROR(365/H32,0) -> 303.90459 | I38: =IFERROR(365/I32,0) -> 256.20072 | J38: =IFERROR(365/J32,0) -> 222.35691 | ... L38: =IFERROR(365/L32,0) -> 304.57717 | N38: =IFERROR(AVERAGE(C38:L38),0) -> 229.33098 | O38: =IFERROR(MEDIAN(C38:L38),0) -> 216.74409
B39: Inventory Days | C39: =IFERROR(365/C33,0) -> 54.603776 | D39: =IFERROR(365/D33,0) -> 49.663454 | E39: =IFERROR(365/E33,0) -> 47.491198 | F39: =IFERROR(365/F33,0) -> 44.566671 | G39: =IFERROR(365/G33,0) -> 48.993645 | H39: =IFERROR(365/H33,0) -> 51.631754 | I39: =IFERROR(365/I33,0) -> 51.436042 | J39: =IFERROR(365/J33,0) -> 43.85447 | ... L39: =IFERROR(365/L33,0) -> 46.67019 | N39: =IFERROR(AVERAGE(C39:L39),0) -> 48.253635 | O39: =IFERROR(MEDIAN(C39:L39),0) -> 48.242422
B40: Cash Conversion Cycle | C40: =IFERROR(C37+C39-C38,0) -> -92.16922 | D40: =IFERROR(D37+D39-D38,0) -> -108.1414 | E40: =IFERROR(E37+E39-E38,0) -> -139.01878 | F40: =IFERROR(F37+F39-F38,0) -> -123.19245 | G40: =IFERROR(G37+G39-G38,0) -> -151.59581 | H40: =IFERROR(H37+H39-H38,0) -> -238.62841 | I40: =IFERROR(I37+I39-I38,0) -> -189.20314 | J40: =IFERROR(J37+J39-J38,0) -> -159.95119 | ... L40: =IFERROR(L37+L39-L38,0) -> -235.82344 | N40: =IFERROR(AVERAGE(C40:L40),0) -> -165.61275 | O40: =IFERROR(MEDIAN(C40:L40),0) -> -155.7735
B42: CFO/Sales | C42: =IFERROR(Historicals!C89/Historicals!C10,0) -> 0.12959051 | D42: =IFERROR(Historicals!D89/Historicals!D10,0) -> 0.15635366 | E42: =IFERROR(Historicals!E89/Historicals!E10,0) -> 0.17045998 | F42: =IFERROR(Historicals!F89/Historicals!F10,0) -> 0.14754515 | G42: =IFERROR(Historicals!G89/Historicals!G10,0) -> 0.19161451 | H42: =IFERROR(Historicals!H89/Historicals!H10,0) -> 0.19484137 | I42: =IFERROR(Historicals!I89/Historicals!I10,0) -> 0.17252031 | J42: =IFERROR(Historicals!J89/Historicals!J10,0) -> 0.16492242 | ... L42: =IFERROR(Historicals!L89/Historicals!L10,0) -> 0.188305 | N42: =IFERROR(AVERAGE(C42:L42),0) -> 0.17660721 | O42: =IFERROR(MEDIAN(C42:L42),0) -> 0.17149014
B43: CFO/Total Assets | C43: =IFERROR(Historicals!C89/Historicals!C70,0) -> 0.28195768 | D43: =IFERROR(Historicals!D89/Historicals!D70,0) -> 0.33012861 | E43: =IFERROR(Historicals!E89/Historicals!E70,0) -> 0.33921173 | F43: =IFERROR(Historicals!F89/Historicals!F70,0) -> 0.31134253 | G43: =IFERROR(Historicals!G89/Historicals!G70,0) -> 0.37825634 | H43: =IFERROR(Historicals!H89/Historicals!H70,0) -> 0.13329939 | I43: =IFERROR(Historicals!I89/Historicals!I70,0) -> 0.1283295 | J43: =IFERROR(Historicals!J89/Historicals!J70,0) -> 0.1367188 | ... L43: =IFERROR(Historicals!L89/Historicals!L70,0) -> 0.14882987 | N43: =IFERROR(AVERAGE(C43:L43),0) -> 0.23851594 | O43: =IFERROR(MEDIAN(C43:L43),0) -> 0.23952131
B44: CFO/Total Debt | C44: =IFERROR(Historicals!C89/Historicals!C55,0) -> 23.564972 | D44: =IFERROR(Historicals!D89/Historicals!D55,0) -> 18.718412 | E44: =IFERROR(Historicals!E89/Historicals!E55,0) -> 0 | F44: =IFERROR(Historicals!F89/Historicals!F55,0) -> 58.585859 | G44: =IFERROR(Historicals!G89/Historicals!G55,0) -> 0 | H44: =IFERROR(Historicals!H89/Historicals!H55,0) -> 0 | I44: =IFERROR(Historicals!I89/Historicals!I55,0) -> 8.674976 | J44: =IFERROR(Historicals!J89/Historicals!J55,0) -> 8.1960623 | ... L44: =IFERROR(Historicals!L89/Historicals!L55,0) -> 7.2123786 | N44: =IFERROR(AVERAGE(C44:L44),0) -> 13.537651 | O44: =IFERROR(MEDIAN(C44:L44),0) -> 8.4355192

Sheet Beta Calculation
B1: HINDUSTAN UNILEVER
B5: Regression Beta
B8: ='Data Sheet'!B1 -> HINDUSTAN UNILEVER LTD | F8: NIFTY 50
B9: Date | C9: Price | D9: Weekly Return | G9: Price | H9: Weekly Return
B10: 45387 | C10: 2232.56 | G10: 22513.7 | J10: Beta Drifting
B11: 45394 | C11: 2198.4 | D11: =C11/C10-1 -> -0.015300821 | G11: 22519.4 | H11: =G11/G10-1 -> 0.00025317918 | J11: Leveraged Raw Beta | K11: =K36 -> 0.56387809
B12: 45401 | C12: 2197.66 | D12: =C12/C11-1 -> -0.00033660844 | G12: 22147 | H12: =G12/G11-1 -> -0.016536853 | J12: Raw Beta Weight | K12: 0.75
B13: 45408 | C13: 2187.08 | D13: =C13/C12-1 -> -0.0048142115 | G13: 22419.95 | H13: =G13/G12-1 -> 0.012324468
B14: 45415 | C14: 2181.17 | D14: =C14/C13-1 -> -0.0027022331 | G14: 22475.85 | H14: =G14/G13-1 -> 0.0024933151 | J14: Market Beta | K14: 1
B15: 45422 | C15: 2320.58 | D15: =C15/C14-1 -> 0.063915238 | G15: 22055.2 | H15: =G15/G14-1 -> -0.018715644 | J15: Market Beta Weight | K15: 0.25
B16: 45429 | C16: 2283.51 | D16: =C16/C15-1 -> -0.015974455 | G16: 22466.1 | H16: =G16/G15-1 -> 0.018630527
B17: 45436 | C17: 2333.18 | D17: =C17/C16-1 -> 0.021751602 | G17: 22957.1 | H17: =G17/G16-1 -> 0.021855151 | J17: Adjusted Beta | K17: =K11*K12+K14*K15 -> 0.67290857
B18: 45443 | C18: 2292.62 | D18: =C18/C17-1 -> -0.017384 | G18: 22530.7 | H18: =G18/G17-1 -> -0.018573775
B19: 45450 | C19: 2536.73 | D19: =C19/C18-1 -> 0.10647643 | G19: 23290.15 | H19: =G19/G18-1 -> 0.033707342 | J19: SUMMARY OUTPUT
B20: 45457 | C20: 2440.84 | D20: =C20/C19-1 -> -0.037800633 | G20: 23465.6 | H20: =G20/G19-1 -> 0.0075332276
B21: 45464 | C21: 2403.52 | D21: =C21/C20-1 -> -0.015289818 | G21: 23501.1 | H21: =G21/G20-1 -> 0.0015128529 | J21: Regression Statistics
B22: 45471 | C22: 2436.85 | D22: =C22/C21-1 -> 0.013867161 | G22: 24010.6 | H22: =G22/G21-1 -> 0.021679836 | J22: Multiple R | K22: 0.3562484
B23: 45478 | C23: 2507.73 | D23: =C23/C22-1 -> 0.029086731 | G23: 24323.85 | H23: =G23/G22-1 -> 0.013046321 | J23: R Square | K23: 0.12691292
B24: 45485 | C24: 2581.77 | D24: =C24/C23-1 -> 0.02952471 | G24: 24502.15 | H24: =G24/G23-1 -> 0.0073302541 | J24: Adjusted R Square | K24: 0.11835324
B25: 45492 | C25: 2684.4 | D25: =C25/C24-1 -> 0.039751798 | G25: 24530.9 | H25: =G25/G24-1 -> 0.0011733664 | J25: Standard Error | K25: 0.026585768
B26: 45499 | C26: 2669.73 | D26: =C26/C25-1 -> -0.0054649084 | G26: 24834.85 | H26: =G26/G25-1 -> 0.012390495 | J26: Observations | K26: 104
B27: 45506 | C27: 2651.77 | D27: =C27/C26-1 -> -0.006727272 | G27: 24717.7 | H27: =G27/G26-1 -> -0.0047171616
B28: 45513 | C28: 2706.01 | D28: =C28/C27-1 -> 0.020454263 | G28: 24367.5 | H28: =G28/G27-1 -> -0.014167985 | J28: ANOVA
B29: 45520 | C29: 2706.5 | D29: =C29/C28-1 -> 0.00018107841 | G29: 24541.15 | H29: =G29/G28-1 -> 0.0071262953 | K29: df | L29: SS | M29: MS | N29: F | O29: Significance F
B30: 45527 | C30: 2770.3 | D30: =C30/C29-1 -> 0.02357288 | G30: 24823.15 | H30: =G30/G29-1 -> 0.011490904 | J30: Regression | K30: 1 | L30: 0.010479653 | M30: 0.010479653 | N30: 14.826835 | O30: 0.00020589429
B31: 45534 | C31: 2735.05 | D31: =C31/C30-1 -> -0.012724254 | G31: 25235.9 | H31: =G31/G30-1 -> 0.016627624 | J31: Residual | K31: 102 | L31: 0.072093915 | M31: 0.00070680308
B32: 45541 | C32: 2794.47 | D32: =C32/C31-1 -> 0.02172538 | G32: 24852.15 | H32: =G32/G31-1 -> -0.015206511 | J32: Total | K32: 103 | L32: 0.082573567
B33: 45548 | C33: 2888.49 | D33: =C33/C32-1 -> 0.03364502 | G33: 25356.5 | H33: =G33/G32-1 -> 0.020294019
B34: 45555 | C34: 2933.43 | D34: =C34/C33-1 -> 0.015558302 | G34: 25790.95 | H34: =G34/G33-1 -> 0.017133674 | K34: Coefficients | L34: Standard Error | M34: t Stat | N34: P-value | O34: Lower 95% | P34: Upper 95% | Q34: Lower 95.0% | R34: Upper 95.0%
B35: 45562 | C35: 2920.04 | D35: =C35/C34-1 -> -0.0045646223 | G35: 26178.95 | H35: =G35/G34-1 -> 0.015044037 | J35: Intercept | K35: -0.00044596289 | L35: 0.002606976 | M35: -0.17106521 | N35: 0.86451139 | O35: -0.0056168875 | P35: 0.0047249617 | Q35: -0.0056168875 | R35: 0.0047249617
B36: 45569 | C36: 2804.71 | D36: =C36/C35-1 -> -0.039496034 | G36: 25014.6 | H36: =G36/G35-1 -> -0.044476574 | J36: X Variable 1 | K36: 0.56387809 | L36: 0.14644043 | M36: 3.8505629 | N36: 0.00020589429 | O36: 0.27341419 | P36: 0.85434198 | Q36: 0.27341419 | R36: 0.85434198
B37: 45576 | C37: 2737.47 | D37: =C37/C36-1 -> -0.023973958 | G37: 24964.25 | H37: =G37/G36-1 -> -0.0020128245
B38: 45583 | C38: 2673.57 | D38: =C38/C37-1 -> -0.023342722 | G38: 24854.05 | H38: =G38/G37-1 -> -0.0044143125
B39: 45590 | C39: 2488.39 | D39: =C39/C38-1 -> -0.069263195 | G39: 24180.8 | H39: =G39/G38-1 -> -0.027088141
B40: 45597 | C40: 2499.02 | D40: =C40/C39-1 -> 0.0042718384 | G40: 24304.35 | H40: =G40/G39-1 -> 0.0051094257
B41: 45604 | C41: 2468.65 | D41: =C41/C40-1 -> -0.012152764 | G41: 24148.2 | H41: =G41/G40-1 -> -0.0064247758
B42: 45610 | C42: 2352.03 | D42: =C42/C41-1 -> -0.047240395 | G42: 23532.7 | H42: =G42/G41-1 -> -0.025488442
B43: 45618 | C43: 2407.51 | D43: =C43/C42-1 -> 0.023588135 | G43: 23907.25 | H43: =G43/G42-1 -> 0.015916151
B44: 45625 | C44: 2457.57 | D44: =C44/C43-1 -> 0.020793268 | G44: 24131.1 | H44: =G44/G43-1 -> 0.0093632685
B45: 45632 | C45: 2445.66 | D45: =C45/C44-1 -> -0.0048462506 | G45: 24677.8 | H45: =G45/G44-1 -> 0.022655411
B46: 45639 | C46: 2352.43 | D46: =C46/C45-1 -> -0.038120589 | G46: 24768.3 | H46: =G46/G45-1 -> 0.0036672637
B47: 45646 | C47: 2298.77 | D47: =C47/C46-1 -> -0.022810456 | G47: 23587.5 | H47: =G47/G46-1 -> -0.047673841
B48: 45653 | C48: 2303.99 | D48: =C48/C47-1 -> 0.0022707796 | G48: 23813.4 | H48: =G48/G47-1 -> 0.0095771065
... B114: 46111 | C114: 2055.8 | D114: =C114/C113-1 -> -0.009253012 | G114: 22331.4 | H114: =G114/G113-1 -> -0.021393889

Sheet Peer Beta
B2: Regression Beta
B4: NIFTY 50 | F4: =WACC!B13 -> ITC | J4: =WACC!B14 -> Hindustan Foods | N4: =WACC!B15 -> Nestle India | R4: =WACC!B16 -> Godrej Consumer | V4: =WACC!B17 -> Britannia Inds.
B5: Date | C5: Price | D5: Weekly Return | G5: Price | H5: Weekly Return | K5: Price | L5: Weekly Return | O5: Price | P5: Weekly Return | S5: Price | T5: Weekly Return | W5: Price | X5: Weekly Return
B6: 45387 | C6: 22513.7 | G6: 403.88 | K6: 522.6 | O6: 1269.05 | S6: 1209.35 | W6: 4811.55
B7: 45394 | C7: 22519.4 | D7: =C7/C6-1 -> 0.00025317918 | G7: 406.01 | H7: =G7/G6-1 -> 0.0052738437 | K7: 520.05 | L7: =K7/K6-1 -> -0.0048794489 | O7: 1268.08 | P7: =O7/O6-1 -> -0.00076435129 | S7: 1199.5 | T7: =S7/S6-1 -> -0.0081448712 | W7: 4749.65 | X7: =W7/W6-1 -> -0.012864877
B8: 45401 | C8: 22147 | D8: =C8/C7-1 -> -0.016536853 | G8: 401 | H8: =G8/G7-1 -> -0.012339598 | K8: 496.7 | L8: =K8/K7-1 -> -0.044899529 | O8: 1218.55 | P8: =O8/O7-1 -> -0.03905905 | S8: 1169.05 | T8: =S8/S7-1 -> -0.025385577 | W8: 4668.1 | X8: =W8/W7-1 -> -0.017169686
B9: 45408 | C9: 22419.95 | D9: =C9/C8-1 -> 0.012324468 | G9: 415.31 | H9: =G9/G8-1 -> 0.035685786 | K9: 502.2 | L9: =K9/K8-1 -> 0.011073082 | O9: 1241.9 | P9: =O9/O8-1 -> 0.019162119 | S9: 1202.15 | T9: =S9/S8-1 -> 0.028313588 | W9: 4797.55 | X9: =W9/W8-1 -> 0.027730768
B10: 45415 | C10: 22475.85 | D10: =C10/C9-1 -> 0.0024933151 | G10: 411.81 | H10: =G10/G9-1 -> -0.0084274397 | K10: 507.25 | L10: =K10/K9-1 -> 0.010055755 | O10: 1227.8 | P10: =O10/O9-1 -> -0.011353571 | S10: 1251.55 | T10: =S10/S9-1 -> 0.041093042 | W10: 4745.15 | X10: =W10/W9-1 -> -0.010922242
B11: 45422 | C11: 22055.2 | D11: =C11/C10-1 -> -0.018715644 | G11: 408.93 | H11: =G11/G10-1 -> -0.0069935164 | K11: 495.5 | L11: =K11/K10-1 -> -0.02316412 | O11: 1266.38 | P11: =O11/O10-1 -> 0.031422056 | S11: 1320.95 | T11: =S11/S10-1 -> 0.05545124 | W11: 5068.6 | X11: =W11/W10-1 -> 0.068164336
B12: 45429 | C12: 22466.1 | D12: =C12/C11-1 -> 0.018630527 | G12: 412.14 | H12: =G12/G11-1 -> 0.0078497542 | K12: 497.2 | L12: =K12/K11-1 -> 0.0034308779 | O12: 1222.6 | P12: =O12/O11-1 -> -0.034570982 | S12: 1295.45 | T12: =S12/S11-1 -> -0.019304289 | W12: 5087.05 | X12: =W12/W11-1 -> 0.0036400584
B13: 45436 | C13: 22957.1 | D13: =C13/C12-1 -> 0.021855151 | G13: 411.67 | H13: =G13/G12-1 -> -0.0011403892 | K13: 493.4 | L13: =K13/K12-1 -> -0.0076427997 | O13: 1233.55 | P13: =O13/O12-1 -> 0.0089563226 | S13: 1310.35 | T13: =S13/S12-1 -> 0.011501795 | W13: 5243.4 | X13: =W13/W12-1 -> 0.030734905
B14: 45443 | C14: 22530.7 | D14: =C14/C13-1 -> -0.018573775 | G14: 402.28 | H14: =G14/G13-1 -> -0.022809532 | K14: 487.45 | L14: =K14/K13-1 -> -0.012059181 | O14: 1177.73 | P14: =O14/O13-1 -> -0.04525151 | S14: 1269.65 | T14: =S14/S13-1 -> -0.031060404 | W14: 5172.5 | X14: =W14/W13-1 -> -0.013521761
B15: 45450 | C15: 23290.15 | D15: =C15/C14-1 -> 0.033707342 | G15: 414.5 | H15: =G15/G14-1 -> 0.030376852 | K15: 513.25 | L15: =K15/K14-1 -> 0.052928505 | O15: 1251.8 | P15: =O15/O14-1 -> 0.062892174 | S15: 1426.7 | T15: =S15/S14-1 -> 0.12369551 | W15: 5463.25 | X15: =W15/W14-1 -> 0.05621073
B16: 45457 | C16: 23465.6 | D16: =C16/C15-1 -> 0.0075332276 | G16: 406.95 | H16: =G16/G15-1 -> -0.018214717 | K16: 504.45 | L16: =K16/K15-1 -> -0.017145641 | O16: 1271.6 | P16: =O16/O15-1 -> 0.015817223 | S16: 1393 | T16: =S16/S15-1 -> -0.023620943 | W16: 5393 | X16: =W16/W15-1 -> -0.012858646
B17: 45464 | C17: 23501.1 | D17: =C17/C16-1 -> 0.0015128529 | G17: 396.1 | H17: =G17/G16-1 -> -0.026661752 | K17: 500.4 | L17: =K17/K16-1 -> -0.0080285459 | O17: 1248.58 | P17: =O17/O16-1 -> -0.018103177 | S17: 1356.35 | T17: =S17/S16-1 -> -0.026310122 | W17: 5331.3 | X17: =W17/W16-1 -> -0.011440757
B18: 45471 | C18: 24010.6 | D18: =C18/C17-1 -> 0.021679836 | G18: 401.1 | H18: =G18/G17-1 -> 0.012623075 | K18: 535.9 | L18: =K18/K17-1 -> 0.070943245 | O18: 1276.28 | P18: =O18/O17-1 -> 0.022185202 | S18: 1376.45 | T18: =S18/S17-1 -> 0.014819184 | W18: 5475.55 | X18: =W18/W17-1 -> 0.027057191
... B110: 46111 | C110: 22331.4 | D110: =C110/C109-1 -> -0.021393889 | G110: 287.7 | H110: =G110/G109-1 -> -0.023918575 | K110: 510.1 | L110: =K110/K109-1 -> 0.0048261598 | O110: 1174.8 | P110: =O110/O109-1 -> -0.016286372 | S110: 984.7 | T110: =S110/S109-1 -> -0.02398652 | W110: 5426.4 | X110: =W110/W109-1 -> -0.013453567
G113: Beta | H113: =SLOPE(H7:H110,$D$7:$D$110) -> 0.52972916 | K113: Beta | L113: =SLOPE(L7:L110,$D$7:$D$110) -> 1.0167885 | O113: Beta | P113: =SLOPE(P7:P110,$D$7:$D$110) -> 0.81759042 | S113: Beta | T113: =SLOPE(T7:T110,$D$7:$D$110) -> 0.89064309 | W113: Beta | X113: =SLOPE(X7:X110,$D$7:$D$110) -> 0.54348

Sheet Rm
B2: Return on Markets
B5: Year | C5: Annual
B6: 2016 | C6: 0.0301
B7: 2017 | C7: 0.2865
B8: 2018 | C8: 0.0315
B9: 2019 | C9: 0.1202
B10: 2020 | C10: 0.149
B11: 2021 | C11: 0.2412
B12: 2022 | C12: 0.0432
B13: 2023 | C13: 0.1942 | F13: Average Annual Return | G13: =AVERAGE(C6:C15) -> 0.12885
B14: 2024 | C14: 0.0875 | F14: Dividend Yield | G14: 0.0128
B15: 2025 | C15: 0.1051 | F15: Annual Market Return | G15: =G13+G14 -> 0.14165

Sheet Data >

Sheet Data Sheet
A1: COMPANY NAME | B1: HINDUSTAN UNILEVER LTD | E1: =IF(B2<>B3, "A NEW VERSION OF THE WORKSHEET IS AVAILABLE", "")
A2: LATEST VERSION | B2: 2.1 | E2: PLEASE DO NOT MAKE ANY CHANGES TO THIS SHEET
A3: CURRENT VERSION | B3: 2.1
A5: META
A6: Number of shares | B6: =IF(B9>0, B9/B8, 0) -> 234.95913
A7: Face Value | B7: 1
A8: Current Price | B8: 2150.95
A9: Market Capitalization | B9: 505385.33
A15: PROFIT & LOSS
A16: Report Date | B16: 42460 | C16: 42825 | D16: 43190 | E16: 43555 | F16: 43921 | G16: 44286 | H16: 44651 | I16: 45016 | J16: 45382 | K16: 45747
A17: Sales | B17: 32186 | C17: 33162 | D17: 35545 | E17: 39310 | F17: 39783 | G17: 47028 | H17: 52446 | I17: 60580 | J17: 61896 | K17: 63121
A18: Raw Material Cost | B18: 13184 | C18: 13606 | D18: 14233 | E18: 15845 | F18: 15697 | G18: 20141 | H18: 22871 | I18: 28427 | J18: 26822 | K18: 27344
A19: Change in Inventory | B19: -83 | C19: -144 | D19: 72 | E19: -12 | F19: 108 | G19: 405 | H19: 22 | I19: 75 | J19: 11 | K19: 153
A20: Power and Fuel | B20: 309 | C20: 295 | D20: 295 | E20: 308 | F20: 299 | G20: 339 | H20: 318 | I20: 384 | J20: 446 | K20: 427
A21: Other Mfr. Exp | B21: 2966 | C21: 2887 | D21: 2998 | E21: 3041 | F21: 2906 | G21: 2868 | H21: 3354 | I21: 3791 | J21: 3385 | K21: 3834
A22: Employee Cost | B22: 1680 | C22: 1743 | D22: 1860 | E22: 1875 | F22: 1820 | G22: 2358 | H22: 2545 | I22: 2854 | J22: 3009 | K22: 3077
A23: Selling and admin | B23: 6741 | C23: 6689 | D23: 7252 | E23: 7796 | F23: 7620 | G23: 7906 | H23: 8164 | I23: 8785 | J23: 10780 | K23: 10693
A24: Other Expenses | B24: 1313 | C24: 1470 | D24: 1480 | E24: 1553 | F24: 1688 | G24: 2195 | H24: 2359 | I24: 2267 | J24: 2806 | K24: 3056
A25: Other Income | B25: 486 | C25: 606 | D25: 353 | E25: 322 | F25: 424 | G25: 170 | H25: 219 | I25: 448 | J25: 817 | K25: 1322
A26: Depreciation | B26: 353 | C26: 432 | D26: 520 | E26: 565 | F26: 1002 | G26: 1074 | H26: 1091 | I26: 1137 | J26: 1216 | K26: 1355
A27: Interest | B27: 17 | C27: 35 | D27: 26 | E27: 33 | F27: 118 | G27: 117 | H27: 106 | I27: 114 | J27: 334 | K27: 395
... A31: Dividend Amount | B31: 3456 | C31: 3672 | D31: 4320 | E31: 4752 | F31: 5400 | G31: 9517.5 | H31: 7990 | I31: 9165 | J31: 9870 | K31: 12455
A40: Quarters
A41: Report Date | B41: 45199 | C41: 45291 | D41: 45382 | E41: 45473 | F41: 45565 | G41: 45657 | H41: 45747 | I41: 45838 | J41: 45930 | K41: 46022
A42: Sales | B42: 15623 | C42: 15567 | D42: 15210 | E42: 15707 | F42: 15926 | G42: 15556 | H42: 15670 | I42: 16514 | J42: 15919 | K42: 16441
A43: Expenses | B43: 11828 | C43: 11902 | D43: 11675 | E43: 11965 | F43: 12139 | G43: 11867 | H43: 12052 | I43: 12797 | J43: 12137 | K43: 12660
A44: Other Income | B44: 178 | C44: 184 | D44: 309 | E44: 209 | F44: 203 | G44: 733 | H44: 171 | I44: 74 | J44: 269 | K44: 4048
A45: Depreciation | B45: 297 | C45: 313 | D45: 320 | E45: 329 | F45: 338 | G45: 318 | H45: 347 | I45: 361 | J45: 322 | K45: 337
A46: Interest | B46: 88 | C46: 91 | D46: 105 | E46: 93 | F46: 110 | G46: 109 | H46: 80 | I46: 127 | J46: 124 | K46: 88
A47: Profit before tax | B47: 3588 | C47: 3445 | D47: 3419 | E47: 3529 | F47: 3542 | G47: 3995 | H47: 3362 | I47: 3303 | J47: 3605 | K47: 7404
A48: Tax | B48: 931 | C48: 937 | D48: 858 | E48: 917 | F48: 947 | G48: 1006 | H48: 887 | I48: 535 | J48: 911 | K48: 801
A49: Net profit | B49: 2656 | C49: 2509 | D49: 2558 | E49: 2610 | F49: 2591 | G49: 2984 | H49: 2464 | I49: 2756 | J49: 2685 | K49: 6607
A50: Operating Profit | B50: 3795 | C50: 3665 | D50: 3535 | E50: 3742 | F50: 3787 | G50: 3689 | H50: 3618 | I50: 3717 | J50: 3782 | K50: 3781
A55: BALANCE SHEET
A56: Report Date | B56: 42460 | C56: 42825 | D56: 43190 | E56: 43555 | F56: 43921 | G56: 44286 | H56: 44651 | I56: 45016 | J56: 45382 | K56: 45747
A57: Equity Share Capital | B57: 216 | C57: 216 | D57: 216 | E57: 216 | F57: 216 | G57: 235 | H57: 235 | I57: 235 | J57: 235 | K57: 235
A58: Reserves | B58: 6357 | C58: 6528 | D58: 7065 | E58: 7651 | F58: 8013 | G58: 47439 | H58: 48826 | I58: 50069 | J58: 50983 | K58: 49167
A59: Borrowings | B59: 177 | C59: 277 | E59: 99 | H59: 1043 | I59: 1219 | J59: 1484 | K59: 1648
A60: Other Liabilities | B60: 8043 | C60: 8685 | D60: 10581 | E60: 10663 | F60: 11924 | G60: 21066 | H60: 20402 | I60: 21554 | J60: 25787 | K60: 28813
A61: Total | B61: 14793 | C61: 15706 | D61: 17862 | E61: 18629 | F61: 20153 | G61: 68740 | H61: 70506 | I61: 73077 | J61: 78489 | K61: 79863
A62: Net Block | B62: 3258 | C62: 4419 | D62: 4528 | E62: 4715 | F62: 5479 | G62: 51443 | H62: 51473 | I62: 52678 | J62: 53744 | K62: 54335
A63: Capital Work in Progress | B63: 408 | C63: 229 | D63: 461 | E63: 406 | F63: 597 | G63: 745 | H63: 1313 | I63: 1132 | J63: 1025 | K63: 1009
A64: Investments | B64: 2592 | C64: 3794 | D64: 2873 | E64: 2716 | F64: 1255 | G64: 2709 | H64: 3521 | I64: 2882 | J64: 4625 | K64: 3810
A65: Other Assets | B65: 8535 | C65: 7264 | D65: 10000 | E65: 10792 | F65: 12822 | G65: 13843 | H65: 14199 | I65: 16385 | J65: 19095 | K65: 20709
A66: Total | B66: 14793 | C66: 15706 | D66: 17862 | E66: 18629 | F66: 20153 | G66: 68740 | H66: 70506 | I66: 73077 | J66: 78489 | K66: 79863
A67: Receivables | B67: 1264 | C67: 1085 | D67: 1310 | E67: 1816 | F67: 1149 | G67: 1758 | H67: 2236 | I67: 3079 | J67: 2997 | K67: 3819
A68: Inventory | B68: 2726 | C68: 2541 | D68: 2513 | E68: 2574 | F68: 2767 | G68: 3579 | H68: 4096 | I68: 4251 | J68: 4022 | K68: 4415
A69: Cash & Bank | B69: 3009 | C69: 1828 | D69: 3485 | E69: 3757 | F69: 5113 | G69: 4471 | H69: 3846 | I69: 4678 | J69: 7559 | K69: 7554
A70: No. of Equity Shares | B70: 2163936971 | C70: 2164349639 | D70: 2164528777 | E70: 2164704405 | F70: 2164704405 | G70: 2349567819 | H70: 2349591262 | I70: 2349591262 | J70: 2349591262 | K70: 2349591262
A71: New Bonus Shares
A72: Face value | B72: 1 | C72: 1 | D72: 1 | E72: 1 | F72: 1 | G72: 1 | H72: 1 | I72: 1 | J72: 1 | K72: 1
A80: CASH FLOW:
A81: Report Date | B81: 42460 | C81: 42825 | D81: 43190 | E81: 43555 | F81: 43921 | G81: 44286 | H81: 44651 | I81: 45016 | J81: 45382 | K81: 45747
A82: Cash from Operating Activity | B82: 4171 | C82: 5185 | D82: 6059 | E82: 5800 | F82: 7623 | G82: 9163 | H82: 9048 | I82: 9991 | J82: 15469 | K82: 11886
A83: Cash from Investing Activity | B83: -282 | C83: -1173 | D83: -1063 | E83: -438 | F83: 1791 | G83: -1228 | H83: -1728 | I83: -1484 | J83: -5324 | K83: 6473
A84: Cash from Financing Activity | B84: -3864 | C84: -4214 | D84: -4975 | E84: -5390 | F84: -6819 | G84: -9309 | H84: -8015 | I84: -8953 | J84: -10034 | K84: -13101
A85: Net Cash Flow | B85: 25 | C85: -202 | D85: 21 | E85: -28 | F85: 2595 | G85: -1374 | H85: -695 | I85: -446 | J85: 111 | K85: 5258
A90: PRICE: | B90: 832.17 | C90: 872.61 | D90: 1276.11 | E90: 1633.53 | F90: 2199.83 | G90: 2327.12 | H90: 1960.7 | I90: 2450.44 | J90: 2167.14 | K90: 2161.88
A92: DERIVED:
A93: Adjusted Equity Shares in Cr | B93: 216.39 | C93: 216.43 | D93: 216.45 | E93: 216.47 | F93: 216.48 | G93: 234.96 | H93: 234.96 | I93: 234.96 | J93: 234.96 | K93: 234.96

Sheet RAW FS
B4: Particulars | C4: 41699 | D4: 42064 | E4: 42430 | F4: 42795 | G4: 43160 | H4: 43525 | I4: 43891 | J4: 44256 | K4: 44621 | L4: 44986 | M4: 45352 | N4: 45717
B6: Equity Capital | C6: 216 | D6: 216 | E6: 216 | F6: 216 | G6: 216 | H6: 216 | I6: 216 | J6: 235 | K6: 235 | L6: 235 | M6: 235 | N6: 235
B7: Reserves | C7: 3321 | D7: 3811 | E7: 6357 | F7: 6528 | G7: 7065 | H7: 7651 | I7: 8013 | J7: 47439 | K7: 48826 | L7: 50069 | M7: 50983 | N7: 49167
B8: Borrowings -
B9: Long term Borrowings | C9: 8 | D9: 7 | E9: 0 | F9: 0 | G9: 0 | H9: 0 | I9: 0 | J9: 0 | K9: 0 | L9: 0 | M9: 0 | N9: 0
B10: Short term Borrowings | C10: 37 | D10: 36 | E10: 177 | F10: 277 | G10: 0 | H10: 99 | I10: 0 | J10: 0 | K10: 0 | L10: 98 | M10: 13 | N10: 1
B11: Lease Liabilities | C11: 0 | D11: 0 | E11: 0 | F11: 0 | G11: 0 | H11: 0 | I11: 0 | J11: 0 | K11: 1043 | L11: 1121 | M11: 1471 | N11: 1647
B12: Preference Capital | C12: 0 | D12: 0 | E12: 0 | F12: 0 | G12: 0 | H12: 0 | I12: 0 | J12: 0 | K12: 0 | L12: 0 | M12: 0 | N12: 0
B13: Other Borrowings | C13: 0 | D13: 0 | E13: 0 | F13: 0 | G13: 0 | H13: 0 | I13: 0 | J13: 0 | K13: 0 | L13: 0 | M13: 0 | N13: 0
B14: Other Liabilities -
B15: Non controlling int | C15: 22 | D15: 25 | E15: 20 | F15: 22 | G15: 20 | H15: 18 | I15: 17 | J15: 20 | K15: 26 | L15: 218 | M15: 205 | N15: 207
B16: Trade Payables | C16: 5825 | D16: 5506 | E16: 5685 | F16: 6186 | G16: 7170 | H16: 7206 | I16: 7535 | J16: 8802 | K16: 9068 | L16: 9574 | M16: 10486 | N16: 11315
B17: Advance from Customers | C17: 37 | D17: 45 | E17: 45 | F17: 78 | G17: 62 | H17: 43 | I17: 158 | J17: 96 | K17: 119 | L17: 98 | M17: 91 | N17: 105
B18: Other liability items | C18: 4287 | D18: 4783 | E18: 2293 | F18: 2399 | G18: 3329 | H18: 3396 | I18: 4214 | J18: 12148 | K18: 11189 | L18: 11664 | M18: 15005 | N18: 17186
B19: Total Liabilities | C19: =SUM(C6:C18) -> 13753 | D19: =SUM(D6:D18) -> 14429 | E19: =SUM(E6:E18) -> 14793 | F19: =SUM(F6:F18) -> 15706 | G19: =SUM(G6:G18) -> 17862 | H19: =SUM(H6:H18) -> 18629 | I19: =SUM(I6:I18) -> 20153 | J19: =SUM(J6:J18) -> 68740 | ... N19: =SUM(N6:N18) -> 79863
B21: Fixed Assets -
B22: Land | C22: 133 | D22: 102 | E22: 88 | F22: 89 | G22: 87 | H22: 86 | I22: 59 | J22: 477 | K22: 477 | L22: 609 | M22: 633 | N22: 628
B23: Building | C23: 1133 | D23: 1173 | E23: 931 | F23: 1210 | G23: 1343 | H23: 1527 | I23: 2044 | J23: 2602 | K23: 2788 | L23: 3101 | M23: 3590 | N23: 3833
B24: Plant Machinery | C24: 3176 | D24: 3481 | E24: 2370 | F24: 3270 | G24: 3691 | H24: 4092 | I24: 5001 | J24: 6097 | K24: 6566 | L24: 7612 | M24: 8946 | N24: 9900
B25: Equipments | C25: 104 | D25: 106 | E25: 41 | F25: 62 | G25: 74 | H25: 95 | I25: 139 | J25: 175 | K25: 181 | L25: 185 | M25: 206 | N25: 245
B26: Furniture n fittings | C26: 102 | D26: 108 | E26: 61 | F26: 66 | G26: 76 | H26: 88 | I26: 154 | J26: 156 | K26: 152 | L26: 161 | M26: 165 | N26: 174
B27: Railway sidings | C27: 0 | D27: 0 | E27: 0 | F27: 0 | G27: 0 | H27: 0 | I27: 0 | J27: 0 | K27: 0 | L27: 0 | M27: 0 | N27: 0
B28: Vehicles | C28: 2 | D28: 1 | E28: 0 | F28: 0 | G28: 0 | H28: 0 | I28: 0 | J28: 0 | K28: 0 | L28: 33 | M28: 39 | N28: 102
B29: Intangible Assets | C29: 247 | D29: 247 | E29: 85 | F29: 455 | G29: 455 | H29: 511 | I29: 511 | J29: 45262 | K29: 45262 | L29: 45692 | M29: 45692 | N29: 45692
B30: Other fixed assets | C30: 183 | D30: 193 | E30: 19 | F30: 19 | G30: 26 | H30: 60 | I30: 71 | J30: 155 | K30: 152 | L30: 171 | M30: 180 | N30: 190
B31: Gross Block | C31: =SUM(C22:C30) -> 5080 | D31: =SUM(D22:D30) -> 5411 | E31: =SUM(E22:E30) -> 3595 | F31: =SUM(F22:F30) -> 5171 | G31: =SUM(G22:G30) -> 5752 | H31: =SUM(H22:H30) -> 6459 | I31: =SUM(I22:I30) -> 7979 | J31: =SUM(J22:J30) -> 54924 | ... N31: =SUM(N22:N30) -> 60764
B32: Accumulated Depreciation | C32: 2333 | D32: 2591 | E32: 337 | F32: 752 | G32: 1224 | H32: 1744 | I32: 2500 | J32: 3481 | K32: 4105 | L32: 4886 | M32: 5707 | N32: 6429
B33: Net Block | C33: =C31-C32 -> 2747 | D33: =D31-D32 -> 2820 | E33: =E31-E32 -> 3258 | F33: =F31-F32 -> 4419 | G33: =G31-G32 -> 4528 | H33: =H31-H32 -> 4715 | I33: =I31-I32 -> 5479 | J33: =J31-J32 -> 51443 | ... N33: =N31-N32 -> 54335
B35: CWIP | C35: 373 | D35: 516 | E35: 408 | F35: 229 | G35: 461 | H35: 406 | I35: 597 | J35: 745 | K35: 1313 | L35: 1132 | M35: 1025 | N35: 1009
B36: Investments | C36: 2838 | D36: 3025 | E36: 2592 | F36: 3794 | G36: 2873 | H36: 2716 | I36: 1255 | J36: 2709 | K36: 3521 | L36: 2882 | M36: 4625 | N36: 3810
B38: Other Assets -
B39: Inventories | C39: 2940 | D39: 2849 | E39: 2726 | F39: 2541 | G39: 2513 | H39: 2574 | I39: 2767 | J39: 3579 | K39: 4096 | L39: 4251 | M39: 4022 | N39: 4415
B40: Trade receivables + | C40: 1017 | D40: 1010 | E40: 1264 | F40: 1085 | G40: 1310 | H40: 1816 | I40: 1149 | J40: 1758 | K40: 2236 | L40: 3079 | M40: 2997 | N40: 3819
B41: Cash Equivalents | C41: 2516 | D41: 2689 | E41: 3009 | F41: 1828 | G41: 3485 | H41: 3757 | I41: 5113 | J41: 4471 | K41: 3846 | L41: 4678 | M41: 7559 | N41: 7554
B42: Loans n Advances | C42: 0 | D42: 0 | E42: 0 | F42: 71 | G42: 40 | H42: 26 | I42: 19 | J42: 78 | K42: 170 | L42: 188 | M42: 172 | N42: 242
B43: Other asset items | C43: 1324 | D43: 1519 | E43: 1536 | F43: 1739 | G43: 2652 | H43: 2619 | I43: 3774 | J43: 3957 | K43: 3851 | L43: 4189 | M43: 4345 | N43: 4679
B44: Total Assets | C44: =SUM(C39:C43,C35:C36,C33) -> 13755 | D44: =SUM(D39:D43,D35:D36,D33) -> 14428 | E44: =SUM(E39:E43,E35:E36,E33) -> 14793 | F44: =SUM(F39:F43,F35:F36,F33) -> 15706 | G44: =SUM(G39:G43,G35:G36,G33) -> 17862 | H44: =SUM(H39:H43,H35:H36,H33) -> 18629 | I44: =SUM(I39:I43,I35:I36,I33) -> 20153 | J44: =SUM(J39:J43,J35:J36,J33) -> 68740 | ... N44: =SUM(N39:N43,N35:N36,N33) -> 79863

Sheet Cash Flow Data
B2: Particulars | C2: 41699 | D2: 42064 | E2: 42430 | F2: 42795 | G2: 43160 | H2: 43525 | I2: 43891 | J2: 44256 | K2: 44621 | L2: 44986 | M2: 45352 | N2: 45717
B3: Cash from Operating Activity - | C3: 3818 | D3: 3292 | E3: 4171 | F3: 5185 | G3: 6059 | H3: 5800 | I3: 7623 | J3: 9163 | K3: 9048 | L3: 9991 | M3: 15469 | N3: 11886
B4: Profit from operations | C4: 4802 | D4: 5510 | E4: 6025 | F4: 6512 | G4: 7485 | H4: 8909 | I4: 9723 | J4: 11672 | K4: 12829 | L4: 14089 | M4: 14537 | N4: 14942
B5: Receivables | C5: -17 | D5: 3 | E5: -257 | F5: 173 | G5: 0 | H5: 0 | I5: 0 | J5: 0 | K5: 0 | L5: 0 | M5: 0 | N5: 0
B6: Inventory | C6: -201 | D6: 91 | E6: 89 | F6: 37 | G6: -146 | H6: -195 | I6: -331 | J6: -543 | K6: -758 | L6: -339 | M6: 74 | N6: -584
B7: Payables | C7: 546 | D7: -327 | E7: 164 | F7: 501 | G7: 0 | H7: 0 | I7: 0 | J7: 0 | K7: 0 | L7: 0 | M7: 0 | N7: 0
B8: Loans Advances | C8: -4 | D8: -148 | E8: 0 | F8: 0 | G8: 0 | H8: 0 | I8: 0 | J8: 0 | K8: 0 | L8: 0 | M8: 0 | N8: 0
B9: Operating Deposits | C9: 0 | D9: 0 | E9: 0 | F9: -46 | G9: 0 | H9: 0 | I9: 0 | J9: 0 | K9: 0 | L9: 0 | M9: 0 | N9: 0
B10: Other WC items | C10: 81 | D10: 38 | E10: -77 | F10: -99 | G10: 982 | H10: -147 | I10: 742 | J10: 442 | K10: -242 | L10: -621 | M10: 1239 | N10: -204
B11: Working capital changes | C11: 405 | D11: -342 | E11: -81 | F11: 566 | G11: 836 | H11: -342 | I11: 411 | J11: -101 | K11: -1000 | L11: -960 | M11: 1313 | N11: -788
B12: Direct taxes | C12: -1384 | D12: -1862 | E12: -1765 | F12: -1859 | G12: -2264 | H12: -2767 | I12: -2505 | J12: -2407 | K12: -2784 | L12: -3138 | M12: -381 | N12: -2268
B13: Other operating items | C13: -5 | D13: -14 | E13: -8 | F13: -21 | G13: 0 | H13: 0 | I13: 0 | J13: 0 | K13: 0 | L13: 0 | M13: 0 | N13: 0
... B37: CFO/OP | C37: 1.09 | D37: 0.95 | E37: 1 | F37: 1.11 | G37: 1.11 | H37: 0.96 | I37: 1.03 | J37: 1 | K37: 0.92 | L37: 0.93 | M37: 1.08 | N37: 0.95

Sheet Market Data
B2: S.No. | C2: Name | D2: CMP Rs. | E2: No. Eq. Shares Cr. | F2: Market Capitalisation | G2: Debt Rs.Cr. | H2: Cash End Rs.Cr. | I2: Net Debt | J2: EV | K2: Sales Ann Rs.Cr. | L2: OPM % | M2: EBITDA | N2: NP 12M Rs.Cr.
B3: 1 | C3: Hind. Unilever | D3: 2155.3 | E3: 234.96 | F3: =D3*E3 -> 506409.29 | G3: 1775 | H3: 7554 | I3: =G3-H3 -> -5779 | J3: =F3+G3-H3 -> 500630.29 | K3: 63121 | L3: 0.2308 | M3: =K3*L3 -> 14568.327 | N3: 14540
B4: 2 | C4: ITC | D4: 304.25 | E4: 1252.95 | F4: =D4*E4 -> 381210.04 | G4: 362.97 | H4: 4012.36 | I4: =G4-H4 -> -3649.39 | J4: =F4+G4-H4 -> 377560.65 | K4: 75323.34 | L4: 0.3372 | M4: =K4*L4 -> 25399.03 | N4: 35356.29
B5: 3 | C5: Nestle India | D5: 1249.3 | E5: 192.83 | F5: =D5*E5 -> 240902.52 | G5: 476.85 | H5: 95.65 | I5: =G5-H5 -> 381.2 | J5: =F5+G5-H5 -> 241283.72 | K5: 20201.56 | L5: 0.2249 | M5: =K5*L5 -> 4543.3308 | N5: 3315.9
B6: 4 | C6: Varun Beverages | D6: 431.6 | E6: 338.21 | F6: =D6*E6 -> 145971.44 | G6: 2508.18 | H6: 1998.49 | I6: =G6-H6 -> 509.69 | J6: =F6+G6-H6 -> 146481.13 | K6: 21685.37 | L6: 0.2338 | M6: =K6*L6 -> 5070.0395 | N6: 3062.04
B7: 5 | C7: Britannia Inds. | D7: 5557.5 | E7: 24.09 | F7: =D7*E7 -> 133880.17 | G7: 2196.3 | H7: 312.48 | I7: =G7-H7 -> 1883.82 | J7: =F7+G7-H7 -> 135763.99 | K7: 17942.67 | L7: 0.1845 | M7: =K7*L7 -> 3310.4226 | N7: 2416.46
B8: 6 | C8: Godrej Consumer | D8: 1078.1 | E8: 102.32 | F8: =D8*E8 -> 110311.19 | G8: 4113.49 | H8: 483.06 | I8: =G8-H8 -> 3630.43 | J8: =F8+G8-H8 -> 113941.62 | K8: 14364.29 | L8: 0.202 | M8: =K8*L8 -> 2901.5866 | N8: 1821.6
B9: 7 | C9: Tata Consumer | D9: 1093.7 | E9: 98.96 | F9: =D9*E9 -> 108232.55 | G9: 2576.11 | H9: 2817.86 | I9: =G9-H9 -> -241.75 | J9: =F9+G9-H9 -> 107990.8 | K9: 17618.3 | L9: 0.1346 | M9: =K9*L9 -> 2371.4232 | N9: 1471.5
B10: 8 | C10: Marico | D10: 763.25 | E10: 129.81 | F10: =D10*E10 -> 99077.482 | G10: 575 | H10: 777 | I10: =G10-H10 -> -202 | J10: =F10+G10-H10 -> 98875.482 | K10: 10831 | L10: 0.1741 | M10: =K10*L10 -> 1885.6771 | N10: 1750
B11: 9 | C11: United Spirits | D11: 1268.2 | E11: 72.74 | F11: =D11*E11 -> 92248.868 | G11: 412 | H11: 2030 | I11: =G11-H11 -> -1618 | J11: =F11+G11-H11 -> 90630.868 | K11: 12069 | L11: 0.1823 | M11: =K11*L11 -> 2200.1787 | N11: 1720
B12: 10 | C12: Dabur India | D12: 435.7 | E12: 177.37 | F12: =D12*E12 -> 77280.109 | G12: 1301.43 | H12: 578.01 | I12: =G12-H12 -> 723.42 | J12: =F12+G12-H12 -> 78003.529 | K12: 12563.09 | L12: 0.1861 | M12: =K12*L12 -> 2337.991 | N12: 1819.42
B32: 11 | C32: Colgate-Palmoliv | D32: 1939.1 | E32: 27.2 | F32: =D32*E32 -> 52743.52 | G32: 59.99 | H32: 1095.13 | J32: =F32+G32-H32 -> 51708.38 | K32: 6040.17 | L32: 0.3148 | M32: =K32*L32 -> 1901.4455 | N32: 1326.99
B33: 12 | C33: Patanjali Foods | D33: 467.35 | E33: 108.81 | F33: =D33*E33 -> 50852.354 | G33: 2895.22 | H33: 275.3 | J33: =F33+G33-H33 -> 53472.274 | K33: 34156.97 | L33: 0.0471 | M33: =K33*L33 -> 1608.7933 | N33: 1649.39
B34: 13 | C34: United Breweries | D34: 1454.2 | E34: 26.44 | F34: =D34*E34 -> 38449.048 | G34: 776.87 | H34: 442.88 | J34: =F34+G34-H34 -> 38783.038 | K34: 8915.09 | L34: 0.0916 | M34: =K34*L34 -> 816.62224 | N34: 409.28
B35: 14 | C35: Radico Khaitan | D35: 2792.7 | E35: 13.39 | F35: =D35*E35 -> 37394.253 | G35: 623.5 | H35: 57.15 | J35: =F35+G35-H35 -> 37960.603 | K35: 4842.64 | L35: 0.1563 | M35: =K35*L35 -> 756.90463 | N35: 518.1
B36: 15 | C36: Godfrey Phillips | D36: 2101.6 | E36: 15.6 | F36: =D36*E36 -> 32784.96 | G36: 175.26 | H36: 30.3 | J36: =F36+G36-H36 -> 32929.92 | K36: 5611.01 | L36: 0.2106 | M36: =K36*L36 -> 1181.6787 | N36: 1284.17
B37: 16 | C37: P & G Hygiene | D37: 9788 | E37: 3.25 | F37: =D37*E37 -> 31811 | G37: 2.06 | H37: 480.7 | J37: =F37+G37-H37 -> 31332.36 | K37: 3374.42 | L37: 0.2678 | M37: =K37*L37 -> 903.66968 | N37: 859.48
B38: 17 | C38: Gillette India | D38: 7704 | E38: 3.26 | F38: =D38*E38 -> 25115.04 | G38: 0.05 | H38: 419.14 | J38: =F38+G38-H38 -> 24695.95 | K38: 2234.84 | L38: 0.2899 | M38: =K38*L38 -> 647.88012 | N38: 620.48
B39: 18 | C39: AWL Agri Busine. | D39: 182.26 | E39: 129.97 | F39: =D39*E39 -> 23688.332 | G39: 1095.97 | H39: 2325.14 | J39: =F39+G39-H39 -> 22459.162 | K39: 63672.24 | L39: 0.0289 | M39: =K39*L39 -> 1840.1277 | N39: 942.49
B40: 19 | C40: Hatsun Agro | D40: 924.35 | E40: 22.27 | F40: =D40*E40 -> 20585.274 | G40: 2009.95 | H40: 61.84 | J40: =F40+G40-H40 -> 22533.385 | K40: 8667.24 | L40: 0.1256 | M40: =K40*L40 -> 1088.6053 | N40: 385.04
B41: 20 | C41: Avanti Feeds | D41: 1459.1 | E41: 13.62 | F41: =D41*E41 -> 19872.942 | G41: 15.02 | H41: 898.66 | J41: =F41+G41-H41 -> 18989.302 | K41: 5612.26 | L41: 0.1271 | M41: =K41*L41 -> 713.31825 | N41: 675.14
B42: 21 | C42: Emami | D42: 424.15 | E42: 43.65 | F42: =D42*E42 -> 18514.147 | G42: 71.96 | H42: 272.9 | J42: =F42+G42-H42 -> 18313.207 | K42: 3809.19 | L42: 0.2598 | M42: =K42*L42 -> 989.62756 | N42: 794.26
B43: 22 | C43: Bikaji Foods | D43: 640.6 | E43: 25.07 | F43: =D43*E43 -> 16059.842 | G43: 309.73 | H43: 219.05 | J43: =F43+G43-H43 -> 16150.522 | K43: 2621.85 | L43: 0.1376 | M43: =K43*L43 -> 360.76656 | N43: 238.46
... B46: 25 | C46: DOMS Industries | D46: 2408.6 | E46: 6.07 | F46: =D46*E46 -> 14620.202 | G46: 161.43 | H46: 225.37 | J46: =F46+G46-H46 -> 14556.262 | K46: 1912.63 | L46: 0.1748 | M46: =K46*L46 -> 334.32772 | N46: 232.65
